<?xml version='1.0' encoding='UTF-8'?>
<!DOCTYPE trafegos>
<trafegos VERSION="0001" CODE="1961" FORMAT="NEWTON">

  <trafego nTrf="1">
    <designador>BE58</designador>
    <ssr>1010</ssr>
    <indicativo>PTKUA</indicativo>
    <origem>SWSI</origem>
    <destino>SBAT</destino>
    <temptrafego>0</temptrafego>
    <coord>
      <tipo>L</tipo>
      <cpoA>-11.43463</cpoA>
      <cpoB>-55.585</cpoB>
    </coord>
    <altitude>30</altitude>
    <velocidade>150</velocidade>
    <procedimento>TRJ31171</procedimento>
    <niveltrj>105</niveltrj>
    <veltrj>200</veltrj>
  </trafego>

  <trafego nTrf="2">
    <designador>MU2B</designador>
    <ssr>6415</ssr>
    <indicativo>PPTHO</indicativo>
    <origem>SBEK</origem>
    <destino>SWBR</destino>
    <temptrafego>0</temptrafego>
    <coord>
      <tipo>L</tipo>
      <cpoA>-6.15959</cpoA>
      <cpoB>-57.80437</cpoB>
    </coord>
    <altitude>60</altitude>
    <velocidade>200</velocidade>
    <procedimento>TRJ31492</procedimento>
    <niveltrj>180</niveltrj>
    <veltrj>275</veltrj>
  </trafego>

  <trafego nTrf="3">
    <designador>E145</designador>
    <ssr>4003</ssr>
    <indicativo>FAB6500</indicativo>
    <origem>SBCC</origem>
    <destino>SWSI</destino>
    <temptrafego>0</temptrafego>
    <coord>
      <tipo>L</tipo>
      <cpoA>-9.52271</cpoA>
      <cpoB>-55.12559</cpoB>
    </coord>
    <altitude>70</altitude>
    <velocidade>180</velocidade>
    <procedimento>TRJ31163</procedimento>
    <niveltrj>200</niveltrj>
    <veltrj>250</veltrj>
  </trafego>

  <trafego nTrf="4">
    <designador>BE58</designador>
    <ssr>3656</ssr>
    <indicativo>PREPM</indicativo>
    <origem>SBEG</origem>
    <destino>SBEK</destino>
    <temptrafego>0</temptrafego>
    <coord>
      <tipo>L</tipo>
      <cpoA>-3.45639</cpoA>
      <cpoB>-60.05467</cpoB>
    </coord>
    <altitude>70</altitude>
    <velocidade>200</velocidade>
    <procedimento>TRJ32713</procedimento>
    <niveltrj>210</niveltrj>
    <veltrj>275</veltrj>
  </trafego>

  <trafego nTrf="5">
    <designador>MU2B</designador>
    <ssr>4557</ssr>
    <indicativo>PTHTH</indicativo>
    <origem>SWFN</origem>
    <destino>SWHT</destino>
    <temptrafego>0</temptrafego>
    <coord>
      <tipo>L</tipo>
      <cpoA>-3.35897</cpoA>
      <cpoB>-60.32232</cpoB>
    </coord>
    <altitude>90</altitude>
    <velocidade>200</velocidade>
    <procedimento>TRJ32712</procedimento>
    <niveltrj>240</niveltrj>
    <veltrj>275</veltrj>
  </trafego>

  <trafego nTrf="6">
    <designador>E135</designador>
    <ssr>6623</ssr>
    <indicativo>PRWZM</indicativo>
    <origem>SBEG</origem>
    <destino>KMIA</destino>
    <temptrafego>0</temptrafego>
    <coord>
      <tipo>L</tipo>
      <cpoA>-2.6791</cpoA>
      <cpoB>-59.99386</cpoB>
    </coord>
    <altitude>100</altitude>
    <velocidade>350</velocidade>
    <procedimento>TRJ32107</procedimento>
    <niveltrj>400</niveltrj>
    <veltrj>430</veltrj>
  </trafego>

  <trafego nTrf="7">
    <designador>B737</designador>
    <ssr>6614</ssr>
    <indicativo>GLO1991</indicativo>
    <origem>SBEG</origem>
    <destino>SBSN</destino>
    <temptrafego>0</temptrafego>
    <coord>
      <tipo>L</tipo>
      <cpoA>-3.15359</cpoA>
      <cpoB>-59.93286</cpoB>
    </coord>
    <altitude>120</altitude>
    <velocidade>250</velocidade>
    <procedimento>TRJ32108</procedimento>
    <niveltrj>350</niveltrj>
    <veltrj>450</veltrj>
  </trafego>

  <trafego nTrf="8">
    <designador>AT72</designador>
    <ssr>6733</ssr>
    <indicativo>TTL9921</indicativo>
    <origem>SBUY</origem>
    <destino>SBEG</destino>
    <temptrafego>0</temptrafego>
    <coord>
      <tipo>L</tipo>
      <cpoA>-4.88333</cpoA>
      <cpoB>-65.35383</cpoB>
    </coord>
    <altitude>120</altitude>
    <velocidade>150</velocidade>
    <procedimento>TRJ30041</procedimento>
    <niveltrj>210</niveltrj>
    <veltrj>260</veltrj>
  </trafego>

  <trafego nTrf="9">
    <designador>B738</designador>
    <ssr>6335</ssr>
    <indicativo>GLO1235</indicativo>
    <origem>SBBV</origem>
    <destino>SBEG</destino>
    <temptrafego>0</temptrafego>
    <coord>
      <tipo>L</tipo>
      <cpoA>2.38394</cpoA>
      <cpoB>-60.91029</cpoB>
    </coord>
    <altitude>120</altitude>
    <velocidade>300</velocidade>
    <procedimento>TRJ32600</procedimento>
    <niveltrj>370</niveltrj>
    <veltrj>460</veltrj>
  </trafego>

  <trafego nTrf="10">
    <designador>B757</designador>
    <ssr>6351</ssr>
    <indicativo>TUS6500</indicativo>
    <origem>SBGR</origem>
    <destino>SBEG</destino>
    <temptrafego>0</temptrafego>
    <coord>
      <tipo>L</tipo>
      <cpoA>-11.41333</cpoA>
      <cpoB>-51.74053</cpoB>
    </coord>
    <altitude>340</altitude>
    <velocidade>460</velocidade>
    <procedimento>TRJ31471</procedimento>
    <niveltrj>340</niveltrj>
    <veltrj>460</veltrj>
  </trafego>

  <trafego nTrf="11">
    <designador>B738</designador>
    <ssr>6431</ssr>
    <indicativo>GLO1130</indicativo>
    <origem>SBBR</origem>
    <destino>SBEG</destino>
    <temptrafego>0</temptrafego>
    <coord>
      <tipo>L</tipo>
      <cpoA>-5.74783</cpoA>
      <cpoB>-56.86767</cpoB>
    </coord>
    <altitude>340</altitude>
    <velocidade>480</velocidade>
    <procedimento>TRJ31492</procedimento>
    <niveltrj>340</niveltrj>
    <veltrj>480</veltrj>
  </trafego>

  <trafego nTrf="12">
    <designador>B777</designador>
    <ssr>6436</ssr>
    <indicativo>AAL950</indicativo>
    <origem>SBGR</origem>
    <destino>KJFK</destino>
    <temptrafego>0</temptrafego>
    <coord>
      <tipo>L</tipo>
      <cpoA>-12.19967</cpoA>
      <cpoB>-53.051</cpoB>
    </coord>
    <altitude>360</altitude>
    <velocidade>480</velocidade>
    <procedimento>TRJ31482</procedimento>
    <niveltrj>360</niveltrj>
    <veltrj>480</veltrj>
  </trafego>

  <trafego nTrf="13">
    <designador>B767</designador>
    <ssr>6442</ssr>
    <indicativo>COA128</indicativo>
    <origem>SBGL</origem>
    <destino>KIAH</destino>
    <temptrafego>0</temptrafego>
    <coord>
      <tipo>L</tipo>
      <cpoA>-11.36619</cpoA>
      <cpoB>-51.81784</cpoB>
    </coord>
    <altitude>360</altitude>
    <velocidade>480</velocidade>
    <procedimento>TRJ31472</procedimento>
    <niveltrj>360</niveltrj>
    <veltrj>480</veltrj>
  </trafego>

  <trafego nTrf="14">
    <designador>A332</designador>
    <ssr>6422</ssr>
    <indicativo>AEA076</indicativo>
    <origem>SPIM</origem>
    <destino>LEMD</destino>
    <temptrafego>0</temptrafego>
    <coord>
      <tipo>L</tipo>
      <cpoA>0.78567</cpoA>
      <cpoB>-63.94822</cpoB>
    </coord>
    <altitude>370</altitude>
    <velocidade>455</velocidade>
    <proa>55</proa>
    <niveltrj>370</niveltrj>
    <veltrj>455</veltrj>
  </trafego>

  <trafego nTrf="15">
    <designador>A320</designador>
    <ssr>4236</ssr>
    <indicativo>TAM9484</indicativo>
    <origem>MDSD</origem>
    <destino>SBEG</destino>
    <temptrafego>0</temptrafego>
    <coord>
      <tipo>L</tipo>
      <cpoA>2.31805</cpoA>
      <cpoB>-64.00617</cpoB>
    </coord>
    <altitude>370</altitude>
    <velocidade>460</velocidade>
    <procedimento>TRJ30969</procedimento>
    <niveltrj>370</niveltrj>
    <veltrj>460</veltrj>
  </trafego>

  <trafego nTrf="16">
    <designador>B737</designador>
    <ssr>4230</ssr>
    <indicativo>CMP802</indicativo>
    <origem>MPTO</origem>
    <destino>SBEG</destino>
    <temptrafego>0</temptrafego>
    <coord>
      <tipo>L</tipo>
      <cpoA>2.03298</cpoA>
      <cpoB>-70.02388</cpoB>
    </coord>
    <altitude>370</altitude>
    <velocidade>460</velocidade>
    <procedimento>TRJ30981</procedimento>
    <niveltrj>370</niveltrj>
    <veltrj>460</veltrj>
  </trafego>

  <trafego nTrf="17">
    <designador>B737</designador>
    <ssr>6552</ssr>
    <indicativo>GLO1250</indicativo>
    <origem>SBBR</origem>
    <destino>SBEG</destino>
    <temptrafego>0</temptrafego>
    <coord>
      <tipo>L</tipo>
      <cpoA>-11.46327</cpoA>
      <cpoB>-51.83646</cpoB>
    </coord>
    <altitude>380</altitude>
    <velocidade>460</velocidade>
    <procedimento>TRJ31471</procedimento>
    <niveltrj>380</niveltrj>
    <veltrj>460</veltrj>
  </trafego>

  <trafego nTrf="18">
    <designador>B737</designador>
    <ssr>6423</ssr>
    <indicativo>GLO1068</indicativo>
    <origem>SBGL</origem>
    <destino>SBEG</destino>
    <temptrafego>0</temptrafego>
    <coord>
      <tipo>L</tipo>
      <cpoA>-5.74783</cpoA>
      <cpoB>-56.86767</cpoB>
    </coord>
    <altitude>380</altitude>
    <velocidade>460</velocidade>
    <procedimento>TRJ30897</procedimento>
    <niveltrj>380</niveltrj>
    <veltrj>460</veltrj>
  </trafego>

  <trafego nTrf="19">
    <designador>B757</designador>
    <ssr>6470</ssr>
    <indicativo>TUS6503</indicativo>
    <origem>SBEG</origem>
    <destino>SBGR</destino>
    <temptrafego>2</temptrafego>
    <coord>
      <tipo>L</tipo>
      <cpoA>-3.34885</cpoA>
      <cpoB>-59.92989</cpoB>
    </coord>
    <altitude>120</altitude>
    <velocidade>310</velocidade>
    <procedimento>TRJ32101</procedimento>
    <niveltrj>350</niveltrj>
    <veltrj>460</veltrj>
  </trafego>

  <trafego nTrf="20">
    <designador>B738</designador>
    <ssr>6671</ssr>
    <indicativo>GLO1646</indicativo>
    <origem>SBEG</origem>
    <destino>SBBV</destino>
    <temptrafego>3</temptrafego>
    <coord>
      <tipo>L</tipo>
      <cpoA>-2.6791</cpoA>
      <cpoB>-59.99386</cpoB>
    </coord>
    <altitude>110</altitude>
    <velocidade>290</velocidade>
    <procedimento>TRJ32105</procedimento>
    <niveltrj>360</niveltrj>
    <veltrj>460</veltrj>
  </trafego>

  <trafego nTrf="21">
    <designador>E190</designador>
    <ssr>1000</ssr>
    <indicativo>AZU2701</indicativo>
    <origem>SWSI</origem>
    <destino>SBBR</destino>
    <temptrafego>5</temptrafego>
    <coord>
      <tipo>L</tipo>
      <cpoA>-11.98426</cpoA>
      <cpoB>-55.585</cpoB>
    </coord>
    <altitude>100</altitude>
    <velocidade>250</velocidade>
    <procedimento>TRJ31491</procedimento>
    <niveltrj>390</niveltrj>
    <veltrj>460</veltrj>
  </trafego>

  <trafego nTrf="22">
    <designador>A340</designador>
    <ssr>6566</ssr>
    <indicativo>TAM3251</indicativo>
    <origem>SBEG</origem>
    <destino>SBGL</destino>
    <temptrafego>5</temptrafego>
    <coord>
      <tipo>L</tipo>
      <cpoA>-3.34885</cpoA>
      <cpoB>-59.92989</cpoB>
    </coord>
    <altitude>120</altitude>
    <velocidade>320</velocidade>
    <procedimento>TRJ32100</procedimento>
    <niveltrj>390</niveltrj>
    <veltrj>480</veltrj>
  </trafego>

  <trafego nTrf="23">
    <designador>B738</designador>
    <ssr>4232</ssr>
    <indicativo>CMP804</indicativo>
    <origem>SKBO</origem>
    <destino>SBEG</destino>
    <temptrafego>5</temptrafego>
    <coord>
      <tipo>L</tipo>
      <cpoA>2.03298</cpoA>
      <cpoB>-70.02388</cpoB>
    </coord>
    <altitude>350</altitude>
    <velocidade>460</velocidade>
    <procedimento>TRJ30981</procedimento>
    <niveltrj>350</niveltrj>
    <veltrj>460</veltrj>
  </trafego>

  <trafego nTrf="24">
    <designador>A320</designador>
    <ssr>4234</ssr>
    <indicativo>TAM9482</indicativo>
    <origem>KMIA</origem>
    <destino>SBEG</destino>
    <temptrafego>5</temptrafego>
    <coord>
      <tipo>L</tipo>
      <cpoA>2.31805</cpoA>
      <cpoB>-64.00617</cpoB>
    </coord>
    <altitude>390</altitude>
    <velocidade>460</velocidade>
    <procedimento>TRJ30969</procedimento>
    <niveltrj>390</niveltrj>
    <veltrj>460</veltrj>
  </trafego>

  <trafego nTrf="25">
    <designador>C750</designador>
    <ssr>6456</ssr>
    <indicativo>PRXDY</indicativo>
    <origem>TNCP</origem>
    <destino>SBEG</destino>
    <temptrafego>5</temptrafego>
    <coord>
      <tipo>L</tipo>
      <cpoA>3.98572</cpoA>
      <cpoB>-63.08383</cpoB>
    </coord>
    <altitude>450</altitude>
    <velocidade>440</velocidade>
    <procedimento>TRJ30966</procedimento>
    <niveltrj>450</niveltrj>
    <veltrj>440</veltrj>
  </trafego>

  <trafego nTrf="26">
    <designador>A320</designador>
    <ssr>6327</ssr>
    <indicativo>TAM3747</indicativo>
    <origem>SBEG</origem>
    <destino>SBBV</destino>
    <temptrafego>6</temptrafego>
    <coord>
      <tipo>L</tipo>
      <cpoA>-2.6791</cpoA>
      <cpoB>-59.99386</cpoB>
    </coord>
    <altitude>100</altitude>
    <velocidade>250</velocidade>
    <procedimento>TRJ32105</procedimento>
    <niveltrj>330</niveltrj>
    <veltrj>470</veltrj>
  </trafego>

  <trafego nTrf="27">
    <designador>MU2B</designador>
    <ssr>4013</ssr>
    <indicativo>PTREC</indicativo>
    <origem>SBAT</origem>
    <destino>SBEK</destino>
    <temptrafego>10</temptrafego>
    <coord>
      <tipo>L</tipo>
      <cpoA>-9.54028</cpoA>
      <cpoB>-56.04716</cpoB>
    </coord>
    <altitude>60</altitude>
    <velocidade>150</velocidade>
    <procedimento>TRJ32713</procedimento>
    <niveltrj>190</niveltrj>
    <veltrj>200</veltrj>
  </trafego>

  <trafego nTrf="28">
    <designador>E175</designador>
    <ssr>6135</ssr>
    <indicativo>AZU2431</indicativo>
    <origem>SBTF</origem>
    <destino>SBEG</destino>
    <temptrafego>10</temptrafego>
    <coord>
      <tipo>L</tipo>
      <cpoA>-3.38783</cpoA>
      <cpoB>-64.81128</cpoB>
    </coord>
    <altitude>100</altitude>
    <velocidade>200</velocidade>
    <procedimento>TRJ30234</procedimento>
    <niveltrj>370</niveltrj>
    <veltrj>460</veltrj>
  </trafego>

  <trafego nTrf="29">
    <designador>LJ55</designador>
    <ssr>6647</ssr>
    <indicativo>PRLAS</indicativo>
    <origem>SBEG</origem>
    <destino>SBHT</destino>
    <temptrafego>10</temptrafego>
    <coord>
      <tipo>L</tipo>
      <cpoA>-3.26718</cpoA>
      <cpoB>-59.81105</cpoB>
    </coord>
    <altitude>110</altitude>
    <velocidade>290</velocidade>
    <procedimento>TRJ32111</procedimento>
    <niveltrj>370</niveltrj>
    <veltrj>460</veltrj>
  </trafego>

  <trafego nTrf="30">
    <designador>A320</designador>
    <ssr>6142</ssr>
    <indicativo>TAM3541</indicativo>
    <origem>SBBV</origem>
    <destino>SBEG</destino>
    <temptrafego>10</temptrafego>
    <coord>
      <tipo>L</tipo>
      <cpoA>2.38394</cpoA>
      <cpoB>-60.91029</cpoB>
    </coord>
    <altitude>140</altitude>
    <velocidade>300</velocidade>
    <procedimento>TRJ32600</procedimento>
    <niveltrj>390</niveltrj>
    <veltrj>480</veltrj>
  </trafego>

  <trafego nTrf="31">
    <designador>AT45</designador>
    <ssr>6232</ssr>
    <indicativo>PTB2572</indicativo>
    <origem>SBBR</origem>
    <destino>SBAT</destino>
    <temptrafego>10</temptrafego>
    <coord>
      <tipo>L</tipo>
      <cpoA>-12.96</cpoA>
      <cpoB>-53.50133</cpoB>
    </coord>
    <altitude>200</altitude>
    <velocidade>200</velocidade>
    <procedimento>TRJ31171</procedimento>
    <niveltrj>200</niveltrj>
    <veltrj>200</veltrj>
  </trafego>

  <trafego nTrf="32">
    <designador>B763</designador>
    <ssr>6531</ssr>
    <indicativo>TUS6553</indicativo>
    <origem>SBEG</origem>
    <destino>SBGR</destino>
    <temptrafego>12</temptrafego>
    <coord>
      <tipo>L</tipo>
      <cpoA>-3.34885</cpoA>
      <cpoB>-59.92989</cpoB>
    </coord>
    <altitude>120</altitude>
    <velocidade>300</velocidade>
    <procedimento>TRJ32101</procedimento>
    <niveltrj>330</niveltrj>
    <veltrj>460</veltrj>
  </trafego>

  <trafego nTrf="33">
    <designador>A320</designador>
    <ssr>6670</ssr>
    <indicativo>TAM3543</indicativo>
    <origem>SBEG</origem>
    <destino>SBBR</destino>
    <temptrafego>14</temptrafego>
    <coord>
      <tipo>L</tipo>
      <cpoA>-3.34885</cpoA>
      <cpoB>-59.92989</cpoB>
    </coord>
    <altitude>120</altitude>
    <velocidade>300</velocidade>
    <procedimento>TRJ32100</procedimento>
    <niveltrj>350</niveltrj>
    <veltrj>460</veltrj>
  </trafego>

  <trafego nTrf="34">
    <designador>LJ55</designador>
    <ssr>6632</ssr>
    <indicativo>PTKAO</indicativo>
    <origem>SBAT</origem>
    <destino>SWSI</destino>
    <temptrafego>15</temptrafego>
    <coord>
      <tipo>L</tipo>
      <cpoA>-10.31803</cpoA>
      <cpoB>-56.105</cpoB>
    </coord>
    <altitude>60</altitude>
    <velocidade>200</velocidade>
    <procedimento>TRJ31163</procedimento>
    <niveltrj>200</niveltrj>
    <veltrj>200</veltrj>
  </trafego>

  <trafego nTrf="35">
    <designador>BE90</designador>
    <ssr>6246</ssr>
    <indicativo>PPKSK</indicativo>
    <origem>SBAT</origem>
    <destino>SWSI</destino>
    <temptrafego>15</temptrafego>
    <coord>
      <tipo>L</tipo>
      <cpoA>-9.86833</cpoA>
      <cpoB>-56.105</cpoB>
    </coord>
    <altitude>65</altitude>
    <velocidade>100</velocidade>
    <proa>180</proa>
    <niveltrj>125</niveltrj>
    <veltrj>200</veltrj>
  </trafego>

  <trafego nTrf="36">
    <designador>LJ45</designador>
    <ssr>6656</ssr>
    <indicativo>N14BIS</indicativo>
    <origem>SBEG</origem>
    <destino>SBHT</destino>
    <temptrafego>15</temptrafego>
    <coord>
      <tipo>L</tipo>
      <cpoA>-3.26718</cpoA>
      <cpoB>-59.81105</cpoB>
    </coord>
    <altitude>110</altitude>
    <velocidade>300</velocidade>
    <procedimento>TRJ32111</procedimento>
    <niveltrj>350</niveltrj>
    <veltrj>470</veltrj>
  </trafego>

  <trafego nTrf="37">
    <designador>LJ55</designador>
    <ssr>6273</ssr>
    <indicativo>PTOGX</indicativo>
    <origem>SBBR</origem>
    <destino>SWSI</destino>
    <temptrafego>17</temptrafego>
    <coord>
      <tipo>L</tipo>
      <cpoA>-12.19967</cpoA>
      <cpoB>-53.051</cpoB>
    </coord>
    <altitude>380</altitude>
    <velocidade>400</velocidade>
    <procedimento>TRJ31163</procedimento>
    <niveltrj>380</niveltrj>
    <veltrj>400</veltrj>
  </trafego>

  <trafego nTrf="38">
    <designador>C99</designador>
    <ssr>7235</ssr>
    <indicativo>TRACJ28</indicativo>
    <origem>SBMN</origem>
    <destino>SBIH</destino>
    <temptrafego>20</temptrafego>
    <coord>
      <tipo>L</tipo>
      <cpoA>-3.10379</cpoA>
      <cpoB>-60.00114</cpoB>
    </coord>
    <altitude>10</altitude>
    <velocidade>100</velocidade>
    <procedimento>TRJ31477</procedimento>
    <niveltrj>250</niveltrj>
    <veltrj>460</veltrj>
  </trafego>

  <trafego nTrf="39">
    <designador>LJ35</designador>
    <ssr>6626</ssr>
    <indicativo>PTJBO</indicativo>
    <origem>SBEG</origem>
    <destino>SBMY</destino>
    <temptrafego>20</temptrafego>
    <coord>
      <tipo>L</tipo>
      <cpoA>-3.11819</cpoA>
      <cpoB>-60.20173</cpoB>
    </coord>
    <altitude>50</altitude>
    <velocidade>150</velocidade>
    <procedimento>TRJ31506</procedimento>
    <niveltrj>360</niveltrj>
    <veltrj>470</veltrj>
  </trafego>

  <trafego nTrf="40">
    <designador>E190</designador>
    <ssr>6654</ssr>
    <indicativo>AZU2579</indicativo>
    <origem>SBEG</origem>
    <destino>SBTF</destino>
    <temptrafego>20</temptrafego>
    <coord>
      <tipo>L</tipo>
      <cpoA>-3.10637</cpoA>
      <cpoB>-60.40031</cpoB>
    </coord>
    <altitude>120</altitude>
    <velocidade>300</velocidade>
    <procedimento>TRJ32104</procedimento>
    <niveltrj>300</niveltrj>
    <veltrj>470</veltrj>
  </trafego>

  <trafego nTrf="41">
    <designador>LJ55</designador>
    <ssr>6660</ssr>
    <indicativo>PTHAD</indicativo>
    <origem>SBCF</origem>
    <destino>SBAT</destino>
    <temptrafego>20</temptrafego>
    <coord>
      <tipo>L</tipo>
      <cpoA>-12.25208</cpoA>
      <cpoB>-52.98628</cpoB>
    </coord>
    <altitude>380</altitude>
    <velocidade>460</velocidade>
    <procedimento>TRJ31171</procedimento>
    <niveltrj>380</niveltrj>
    <veltrj>460</veltrj>
  </trafego>

  <trafego nTrf="42">
    <designador>B738</designador>
    <ssr>6771</ssr>
    <indicativo>GLO1705</indicativo>
    <origem>SBEG</origem>
    <destino>SBGR</destino>
    <temptrafego>22</temptrafego>
    <coord>
      <tipo>L</tipo>
      <cpoA>-3.34885</cpoA>
      <cpoB>-59.92989</cpoB>
    </coord>
    <altitude>110</altitude>
    <velocidade>300</velocidade>
    <procedimento>TRJ32101</procedimento>
    <niveltrj>350</niveltrj>
    <veltrj>460</veltrj>
  </trafego>

  <trafego nTrf="43">
    <designador>AT72</designador>
    <ssr>1001</ssr>
    <indicativo>PTB2376</indicativo>
    <origem>SWSI</origem>
    <destino>SBAT</destino>
    <temptrafego>23</temptrafego>
    <coord>
      <tipo>L</tipo>
      <cpoA>-10.8675</cpoA>
      <cpoB>-56.12244</cpoB>
    </coord>
    <altitude>80</altitude>
    <velocidade>180</velocidade>
    <procedimento>TRJ31171</procedimento>
    <niveltrj>170</niveltrj>
    <veltrj>260</veltrj>
  </trafego>

  <trafego nTrf="44">
    <designador>E170</designador>
    <ssr>6362</ssr>
    <indicativo>AZU2530</indicativo>
    <origem>SBTF</origem>
    <destino>SBEG</destino>
    <temptrafego>25</temptrafego>
    <coord>
      <tipo>L</tipo>
      <cpoA>-3.38783</cpoA>
      <cpoB>-64.81128</cpoB>
    </coord>
    <altitude>100</altitude>
    <velocidade>160</velocidade>
    <procedimento>TRJ30234</procedimento>
    <niveltrj>350</niveltrj>
    <veltrj>460</veltrj>
  </trafego>

  <trafego nTrf="45">
    <designador>A320</designador>
    <ssr>6326</ssr>
    <indicativo>TAM3598</indicativo>
    <origem>SBEG</origem>
    <destino>SBBE</destino>
    <temptrafego>26</temptrafego>
    <coord>
      <tipo>L</tipo>
      <cpoA>-3.26718</cpoA>
      <cpoB>-59.81105</cpoB>
    </coord>
    <altitude>120</altitude>
    <velocidade>250</velocidade>
    <procedimento>TRJ32108</procedimento>
    <niveltrj>360</niveltrj>
    <veltrj>470</veltrj>
  </trafego>

  <trafego nTrf="46">
    <designador>G5</designador>
    <ssr>6137</ssr>
    <indicativo>N37FL1X</indicativo>
    <origem>SBBV</origem>
    <destino>SBEG</destino>
    <temptrafego>30</temptrafego>
    <coord>
      <tipo>L</tipo>
      <cpoA>2.38394</cpoA>
      <cpoB>-60.91029</cpoB>
    </coord>
    <altitude>100</altitude>
    <velocidade>300</velocidade>
    <procedimento>TRJ32600</procedimento>
    <niveltrj>410</niveltrj>
    <veltrj>460</veltrj>
  </trafego>

  <trafego nTrf="47">
    <designador>B737</designador>
    <ssr>6767</ssr>
    <indicativo>GLO1633</indicativo>
    <origem>SBEG</origem>
    <destino>SBGL</destino>
    <temptrafego>32</temptrafego>
    <coord>
      <tipo>L</tipo>
      <cpoA>-3.34885</cpoA>
      <cpoB>-59.92989</cpoB>
    </coord>
    <altitude>120</altitude>
    <velocidade>300</velocidade>
    <procedimento>TRJ32100</procedimento>
    <niveltrj>370</niveltrj>
    <veltrj>460</veltrj>
  </trafego>

  <trafego nTrf="48">
    <designador>E145</designador>
    <ssr>4271</ssr>
    <indicativo>FAM4101</indicativo>
    <origem>SBGL</origem>
    <destino>SBEG</destino>
    <temptrafego>33</temptrafego>
    <coord>
      <tipo>L</tipo>
      <cpoA>-11.22195</cpoA>
      <cpoB>-51.90112</cpoB>
    </coord>
    <altitude>300</altitude>
    <velocidade>450</velocidade>
    <procedimento>TRJ31471</procedimento>
    <niveltrj>300</niveltrj>
    <veltrj>450</veltrj>
  </trafego>

  <trafego nTrf="49">
    <designador>A320</designador>
    <ssr>6570</ssr>
    <indicativo>TAM3751</indicativo>
    <origem>SBEG</origem>
    <destino>SBBV</destino>
    <temptrafego>34</temptrafego>
    <coord>
      <tipo>L</tipo>
      <cpoA>-2.6791</cpoA>
      <cpoB>-59.99386</cpoB>
    </coord>
    <altitude>100</altitude>
    <velocidade>300</velocidade>
    <procedimento>TRJ32105</procedimento>
    <niveltrj>320</niveltrj>
    <veltrj>460</veltrj>
  </trafego>

  <trafego nTrf="50">
    <designador>BE58</designador>
    <ssr>3456</ssr>
    <indicativo>PTIEB</indicativo>
    <origem>SBEG</origem>
    <destino>SBIH</destino>
    <temptrafego>35</temptrafego>
    <coord>
      <tipo>L</tipo>
      <cpoA>-3.42945</cpoA>
      <cpoB>-59.82982</cpoB>
    </coord>
    <altitude>70</altitude>
    <velocidade>200</velocidade>
    <procedimento>TRJ30070</procedimento>
    <niveltrj>250</niveltrj>
    <veltrj>275</veltrj>
  </trafego>

  <trafego nTrf="51">
    <designador>MU2B</designador>
    <ssr>2526</ssr>
    <indicativo>PRIAD</indicativo>
    <origem>SBIH</origem>
    <destino>SBEG</destino>
    <temptrafego>35</temptrafego>
    <coord>
      <tipo>L</tipo>
      <cpoA>-3.8799</cpoA>
      <cpoB>-56.21286</cpoB>
    </coord>
    <altitude>70</altitude>
    <velocidade>200</velocidade>
    <procedimento>TRJ31492</procedimento>
    <niveltrj>260</niveltrj>
    <veltrj>275</veltrj>
  </trafego>

  <trafego nTrf="52">
    <designador>C680</designador>
    <ssr>6141</ssr>
    <indicativo>VPCAV</indicativo>
    <origem>SBEG</origem>
    <destino>KFLL</destino>
    <temptrafego>35</temptrafego>
    <coord>
      <tipo>L</tipo>
      <cpoA>-2.6894</cpoA>
      <cpoB>-60.38766</cpoB>
    </coord>
    <altitude>100</altitude>
    <velocidade>300</velocidade>
    <procedimento>TRJ32110</procedimento>
    <niveltrj>430</niveltrj>
    <veltrj>450</veltrj>
  </trafego>

  <trafego nTrf="53">
    <designador>A320</designador>
    <ssr>4202</ssr>
    <indicativo>TAM3775</indicativo>
    <origem>SBEG</origem>
    <destino>SBGR</destino>
    <temptrafego>36</temptrafego>
    <coord>
      <tipo>L</tipo>
      <cpoA>-3.34885</cpoA>
      <cpoB>-59.92989</cpoB>
    </coord>
    <altitude>120</altitude>
    <velocidade>300</velocidade>
    <procedimento>TRJ32101</procedimento>
    <niveltrj>390</niveltrj>
    <veltrj>450</veltrj>
  </trafego>

  <trafego nTrf="54">
    <designador>LJ35</designador>
    <ssr>5445</ssr>
    <indicativo>PRTHO</indicativo>
    <origem>SBEK</origem>
    <destino>SWHT</destino>
    <temptrafego>37</temptrafego>
    <coord>
      <tipo>L</tipo>
      <cpoA>-6.15022</cpoA>
      <cpoB>-58.00526</cpoB>
    </coord>
    <altitude>50</altitude>
    <velocidade>200</velocidade>
    <procedimento>TRJ32715</procedimento>
    <niveltrj>105</niveltrj>
    <veltrj>250</veltrj>
  </trafego>

  <trafego nTrf="55">
    <designador>BE58</designador>
    <ssr>1006</ssr>
    <indicativo>PRCLA</indicativo>
    <origem>SWHT</origem>
    <destino>SBEK</destino>
    <temptrafego>37</temptrafego>
    <coord>
      <tipo>L</tipo>
      <cpoA>-7.61678</cpoA>
      <cpoB>-62.90609</cpoB>
    </coord>
    <altitude>90</altitude>
    <velocidade>200</velocidade>
    <procedimento>TRJ32713</procedimento>
    <niveltrj>110</niveltrj>
    <veltrj>260</veltrj>
  </trafego>

  <trafego nTrf="56">
    <designador>LJ35</designador>
    <ssr>4262</ssr>
    <indicativo>N201CC</indicativo>
    <origem>SBBR</origem>
    <destino>SBEG</destino>
    <temptrafego>37</temptrafego>
    <coord>
      <tipo>L</tipo>
      <cpoA>-11.22195</cpoA>
      <cpoB>-51.90112</cpoB>
    </coord>
    <altitude>380</altitude>
    <velocidade>460</velocidade>
    <procedimento>TRJ31471</procedimento>
    <niveltrj>380</niveltrj>
    <veltrj>460</veltrj>
  </trafego>

  <trafego nTrf="57">
    <designador>B737</designador>
    <ssr>6770</ssr>
    <indicativo>GLO1131</indicativo>
    <origem>SBEG</origem>
    <destino>SBBR</destino>
    <temptrafego>38</temptrafego>
    <coord>
      <tipo>L</tipo>
      <cpoA>-3.34885</cpoA>
      <cpoB>-59.92989</cpoB>
    </coord>
    <altitude>120</altitude>
    <velocidade>280</velocidade>
    <procedimento>TRJ32100</procedimento>
    <niveltrj>390</niveltrj>
    <veltrj>430</veltrj>
  </trafego>

  <trafego nTrf="58">
    <designador>BE30</designador>
    <ssr>6611</ssr>
    <indicativo>PTWJS</indicativo>
    <origem>SBMY</origem>
    <destino>SBEG</destino>
    <temptrafego>40</temptrafego>
    <coord>
      <tipo>L</tipo>
      <cpoA>-5.72389</cpoA>
      <cpoB>-61.282</cpoB>
    </coord>
    <altitude>10</altitude>
    <velocidade>100</velocidade>
    <procedimento>TRJ30010</procedimento>
    <niveltrj>360</niveltrj>
    <veltrj>470</veltrj>
  </trafego>

  <trafego nTrf="59">
    <designador>E145</designador>
    <ssr>6636</ssr>
    <indicativo>TRACJ44</indicativo>
    <origem>SBIH</origem>
    <destino>SBMN</destino>
    <temptrafego>40</temptrafego>
    <coord>
      <tipo>L</tipo>
      <cpoA>-4.17671</cpoA>
      <cpoB>-56.0582</cpoB>
    </coord>
    <altitude>10</altitude>
    <velocidade>100</velocidade>
    <procedimento>TRJ30010</procedimento>
    <niveltrj>260</niveltrj>
    <veltrj>240</veltrj>
  </trafego>

  <trafego nTrf="60">
    <designador>E145</designador>
    <ssr>1002</ssr>
    <indicativo>PTB2377</indicativo>
    <origem>SWSI</origem>
    <destino>SBAT</destino>
    <temptrafego>44</temptrafego>
    <coord>
      <tipo>L</tipo>
      <cpoA>-11.88433</cpoA>
      <cpoB>-55.585</cpoB>
    </coord>
    <altitude>50</altitude>
    <velocidade>200</velocidade>
    <procedimento>TRJ31171</procedimento>
    <niveltrj>240</niveltrj>
    <veltrj>290</veltrj>
  </trafego>

  <trafego nTrf="61">
    <designador>E190</designador>
    <ssr>6111</ssr>
    <indicativo>AZU4107</indicativo>
    <origem>SBEG</origem>
    <destino>SWPI</destino>
    <temptrafego>47</temptrafego>
    <coord>
      <tipo>L</tipo>
      <cpoA>-3.1123</cpoA>
      <cpoB>-59.64461</cpoB>
    </coord>
    <altitude>100</altitude>
    <velocidade>220</velocidade>
    <procedimento>TRJ30993</procedimento>
    <niveltrj>210</niveltrj>
    <veltrj>260</veltrj>
  </trafego>

  <trafego nTrf="62">
    <designador>E145</designador>
    <ssr>6132</ssr>
    <indicativo>AZU2501</indicativo>
    <origem>SBTF</origem>
    <destino>SBEG</destino>
    <temptrafego>49</temptrafego>
    <coord>
      <tipo>L</tipo>
      <cpoA>-3.38783</cpoA>
      <cpoB>-64.728</cpoB>
    </coord>
    <altitude>120</altitude>
    <velocidade>210</velocidade>
    <procedimento>TRJ30234</procedimento>
    <niveltrj>310</niveltrj>
    <veltrj>440</veltrj>
  </trafego>

  <trafego nTrf="63">
    <designador>E175</designador>
    <ssr>6133</ssr>
    <indicativo>AZU2496</indicativo>
    <origem>SBAT</origem>
    <destino>SWSI</destino>
    <temptrafego>50</temptrafego>
    <coord>
      <tipo>L</tipo>
      <cpoA>-9.86833</cpoA>
      <cpoB>-56.105</cpoB>
    </coord>
    <altitude>50</altitude>
    <velocidade>210</velocidade>
    <procedimento>TRJ31163</procedimento>
    <niveltrj>220</niveltrj>
    <veltrj>280</veltrj>
  </trafego>

  <trafego nTrf="64">
    <designador>B737</designador>
    <ssr>6336</ssr>
    <indicativo>CMP140</indicativo>
    <origem>SBEG</origem>
    <destino>MPTO</destino>
    <temptrafego>50</temptrafego>
    <coord>
      <tipo>L</tipo>
      <cpoA>-2.7483</cpoA>
      <cpoB>-60.4617</cpoB>
    </coord>
    <altitude>100</altitude>
    <velocidade>250</velocidade>
    <procedimento>TRJ32109</procedimento>
    <niveltrj>380</niveltrj>
    <veltrj>440</veltrj>
  </trafego>

  <trafego nTrf="65">
    <designador>E190</designador>
    <ssr>4030</ssr>
    <indicativo>AZU2419</indicativo>
    <origem>SBEG</origem>
    <destino>SBTF</destino>
    <temptrafego>50</temptrafego>
    <coord>
      <tipo>L</tipo>
      <cpoA>-3.10637</cpoA>
      <cpoB>-60.40031</cpoB>
    </coord>
    <altitude>100</altitude>
    <velocidade>300</velocidade>
    <procedimento>TRJ32104</procedimento>
    <niveltrj>320</niveltrj>
    <veltrj>440</veltrj>
  </trafego>

  <trafego nTrf="66">
    <designador>B763</designador>
    <ssr>6720</ssr>
    <indicativo>LPE2707</indicativo>
    <origem>LEMD</origem>
    <destino>SPIM</destino>
    <temptrafego>50</temptrafego>
    <coord>
      <tipo>L</tipo>
      <cpoA>4.72971</cpoA>
      <cpoB>-59.96941</cpoB>
    </coord>
    <altitude>380</altitude>
    <velocidade>490</velocidade>
    <procedimento>TRJ30917</procedimento>
    <niveltrj>380</niveltrj>
    <veltrj>490</veltrj>
  </trafego>

  <trafego nTrf="67">
    <designador>B763</designador>
    <ssr>6364</ssr>
    <indicativo>TUS6550</indicativo>
    <origem>SBGR</origem>
    <destino>SBEG</destino>
    <temptrafego>51</temptrafego>
    <coord>
      <tipo>L</tipo>
      <cpoA>-11.22195</cpoA>
      <cpoB>-51.90112</cpoB>
    </coord>
    <altitude>340</altitude>
    <velocidade>460</velocidade>
    <procedimento>TRJ31471</procedimento>
    <niveltrj>340</niveltrj>
    <veltrj>460</veltrj>
  </trafego>

  <trafego nTrf="68">
    <designador>A330</designador>
    <ssr>4203</ssr>
    <indicativo>TAM3661</indicativo>
    <origem>SBEG</origem>
    <destino>SBBR</destino>
    <temptrafego>52</temptrafego>
    <coord>
      <tipo>L</tipo>
      <cpoA>-3.34885</cpoA>
      <cpoB>-59.92989</cpoB>
    </coord>
    <altitude>100</altitude>
    <velocidade>300</velocidade>
    <procedimento>TRJ32100</procedimento>
    <niveltrj>350</niveltrj>
    <veltrj>480</veltrj>
  </trafego>

  <trafego nTrf="69">
    <designador>E175</designador>
    <ssr>6365</ssr>
    <indicativo>AZU2499</indicativo>
    <origem>SBAT</origem>
    <destino>SWSI</destino>
    <temptrafego>55</temptrafego>
    <coord>
      <tipo>L</tipo>
      <cpoA>-9.86833</cpoA>
      <cpoB>-56.105</cpoB>
    </coord>
    <altitude>70</altitude>
    <velocidade>180</velocidade>
    <proa>181</proa>
    <niveltrj>160</niveltrj>
    <veltrj>210</veltrj>
  </trafego>

  <trafego nTrf="70">
    <designador>E120</designador>
    <ssr>6134</ssr>
    <indicativo>GUARA35</indicativo>
    <origem>SBBR</origem>
    <destino>SBCC</destino>
    <temptrafego>55</temptrafego>
    <coord>
      <tipo>L</tipo>
      <cpoA>-12.19967</cpoA>
      <cpoB>-53.051</cpoB>
    </coord>
    <altitude>240</altitude>
    <velocidade>250</velocidade>
    <procedimento>TRJ31197</procedimento>
    <niveltrj>240</niveltrj>
    <veltrj>250</veltrj>
  </trafego>

  <trafego nTrf="71">
    <designador>E190</designador>
    <ssr>4266</ssr>
    <indicativo>AZU2379</indicativo>
    <origem>SBBR</origem>
    <destino>SBAT</destino>
    <temptrafego>60</temptrafego>
    <coord>
      <tipo>L</tipo>
      <cpoA>-12.19967</cpoA>
      <cpoB>-53.051</cpoB>
    </coord>
    <altitude>360</altitude>
    <velocidade>440</velocidade>
    <procedimento>TRJ31171</procedimento>
    <niveltrj>360</niveltrj>
    <veltrj>440</veltrj>
  </trafego>

  <trafego nTrf="72">
    <designador>B777</designador>
    <ssr>6736</ssr>
    <indicativo>AAL955</indicativo>
    <origem>KJFK</origem>
    <destino>SAEZ</destino>
    <temptrafego>65</temptrafego>
    <coord>
      <tipo>L</tipo>
      <cpoA>1.06055</cpoA>
      <cpoB>-65.72177</cpoB>
    </coord>
    <altitude>350</altitude>
    <velocidade>470</velocidade>
    <procedimento>TRJ30987</procedimento>
    <niveltrj>350</niveltrj>
    <veltrj>470</veltrj>
  </trafego>

  <trafego nTrf="73">
    <designador>A332</designador>
    <ssr>6615</ssr>
    <indicativo>TAM8087</indicativo>
    <origem>KMCO</origem>
    <destino>SBGR</destino>
    <temptrafego>68</temptrafego>
    <coord>
      <tipo>L</tipo>
      <cpoA>4.40342</cpoA>
      <cpoB>-62.54241</cpoB>
    </coord>
    <altitude>390</altitude>
    <velocidade>470</velocidade>
    <procedimento>TRJ31186</procedimento>
    <niveltrj>390</niveltrj>
    <veltrj>470</veltrj>
  </trafego>

  <trafego nTrf="74">
    <designador>B738</designador>
    <ssr>6175</ssr>
    <indicativo>CMP125</indicativo>
    <origem>SBEG</origem>
    <destino>SKBO</destino>
    <temptrafego>70</temptrafego>
    <coord>
      <tipo>L</tipo>
      <cpoA>-2.69959</cpoA>
      <cpoB>-60.40855</cpoB>
    </coord>
    <altitude>120</altitude>
    <velocidade>300</velocidade>
    <procedimento>TRJ32109</procedimento>
    <niveltrj>380</niveltrj>
    <veltrj>470</veltrj>
  </trafego>

  <trafego nTrf="75">
    <designador>E190</designador>
    <ssr>6020</ssr>
    <indicativo>AZU2615</indicativo>
    <origem>SBAT</origem>
    <destino>SBCY</destino>
    <temptrafego>70</temptrafego>
    <coord>
      <tipo>L</tipo>
      <cpoA>-10.18135</cpoA>
      <cpoB>-56.21893</cpoB>
    </coord>
    <altitude>125</altitude>
    <velocidade>250</velocidade>
    <procedimento>TRJ30990</procedimento>
    <niveltrj>390</niveltrj>
    <veltrj>422</veltrj>
  </trafego>

  <trafego nTrf="76">
    <designador>A320</designador>
    <ssr>6441</ssr>
    <indicativo>TAM8051</indicativo>
    <origem>SVMI</origem>
    <destino>SBGR</destino>
    <temptrafego>70</temptrafego>
    <coord>
      <tipo>L</tipo>
      <cpoA>4.25875</cpoA>
      <cpoB>-62.45272</cpoB>
    </coord>
    <altitude>350</altitude>
    <velocidade>460</velocidade>
    <procedimento>TRJ31186</procedimento>
    <niveltrj>350</niveltrj>
    <veltrj>460</veltrj>
  </trafego>

  <trafego nTrf="77">
    <designador>B738</designador>
    <ssr>6612</ssr>
    <indicativo>GLO1132</indicativo>
    <origem>SBBV</origem>
    <destino>SBEG</destino>
    <temptrafego>75</temptrafego>
    <coord>
      <tipo>L</tipo>
      <cpoA>2.46475</cpoA>
      <cpoB>-60.89015</cpoB>
    </coord>
    <altitude>110</altitude>
    <velocidade>290</velocidade>
    <procedimento>TRJ32600</procedimento>
    <niveltrj>320</niveltrj>
    <veltrj>460</veltrj>
  </trafego>

  <trafego nTrf="78">
    <designador>B767</designador>
    <ssr>6641</ssr>
    <indicativo>TAM8057</indicativo>
    <origem>KMIA</origem>
    <destino>SBGL</destino>
    <temptrafego>75</temptrafego>
    <coord>
      <tipo>L</tipo>
      <cpoA>2.21642</cpoA>
      <cpoB>-64.05391</cpoB>
    </coord>
    <altitude>370</altitude>
    <velocidade>470</velocidade>
    <procedimento>TRJ31188</procedimento>
    <niveltrj>370</niveltrj>
    <veltrj>470</veltrj>
  </trafego>

  <trafego nTrf="79">
    <designador>A320</designador>
    <ssr>6643</ssr>
    <indicativo>TAM8017</indicativo>
    <origem>SKBO</origem>
    <destino>SBGR</destino>
    <temptrafego>76</temptrafego>
    <coord>
      <tipo>L</tipo>
      <cpoA>0.96099</cpoA>
      <cpoB>-69.86452</cpoB>
    </coord>
    <altitude>350</altitude>
    <velocidade>470</velocidade>
    <procedimento>TRJ31185</procedimento>
    <niveltrj>350</niveltrj>
    <veltrj>470</veltrj>
  </trafego>

  <trafego nTrf="80">
    <designador>A332</designador>
    <ssr>6543</ssr>
    <indicativo>TAM8091</indicativo>
    <origem>KMIA</origem>
    <destino>SBGR</destino>
    <temptrafego>77</temptrafego>
    <coord>
      <tipo>L</tipo>
      <cpoA>2.23132</cpoA>
      <cpoB>-64.01299</cpoB>
    </coord>
    <altitude>390</altitude>
    <velocidade>480</velocidade>
    <procedimento>TRJ31188</procedimento>
    <niveltrj>390</niveltrj>
    <veltrj>480</veltrj>
  </trafego>

  <trafego nTrf="81">
    <designador>E190</designador>
    <ssr>6521</ssr>
    <indicativo>AZU2965</indicativo>
    <origem>SWPI</origem>
    <destino>SBEG</destino>
    <temptrafego>78</temptrafego>
    <coord>
      <tipo>L</tipo>
      <cpoA>-2.66733</cpoA>
      <cpoB>-56.93972</cpoB>
    </coord>
    <altitude>50</altitude>
    <velocidade>150</velocidade>
    <procedimento>TRJ30896</procedimento>
    <niveltrj>380</niveltrj>
    <veltrj>420</veltrj>
  </trafego>

  <trafego nTrf="82">
    <designador>A320</designador>
    <ssr>4273</ssr>
    <indicativo>TAM3050</indicativo>
    <origem>SBEG</origem>
    <destino>SBGR</destino>
    <temptrafego>78</temptrafego>
    <coord>
      <tipo>L</tipo>
      <cpoA>-3.34885</cpoA>
      <cpoB>-59.92989</cpoB>
    </coord>
    <altitude>100</altitude>
    <velocidade>250</velocidade>
    <procedimento>TRJ32101</procedimento>
    <niveltrj>330</niveltrj>
    <veltrj>460</veltrj>
  </trafego>

  <trafego nTrf="83">
    <designador>AT45</designador>
    <ssr>6540</ssr>
    <indicativo>TTL9920</indicativo>
    <origem>SBEG</origem>
    <destino>SBUY</destino>
    <temptrafego>80</temptrafego>
    <coord>
      <tipo>L</tipo>
      <cpoA>-3.10637</cpoA>
      <cpoB>-60.40031</cpoB>
    </coord>
    <altitude>100</altitude>
    <velocidade>250</velocidade>
    <procedimento>TRJ32104</procedimento>
    <niveltrj>390</niveltrj>
    <veltrj>460</veltrj>
  </trafego>

  <trafego nTrf="84">
    <designador>B738</designador>
    <ssr>6560</ssr>
    <indicativo>CMP759</indicativo>
    <origem>MPTO</origem>
    <destino>SBGR</destino>
    <temptrafego>80</temptrafego>
    <coord>
      <tipo>L</tipo>
      <cpoA>1.24233</cpoA>
      <cpoB>-70.2365</cpoB>
    </coord>
    <altitude>370</altitude>
    <velocidade>450</velocidade>
    <procedimento>TRJ31185</procedimento>
    <niveltrj>370</niveltrj>
    <veltrj>450</veltrj>
  </trafego>

  <trafego nTrf="85">
    <designador>B738</designador>
    <ssr>6546</ssr>
    <indicativo>TAM8076</indicativo>
    <origem>SVMI</origem>
    <destino>SBGR</destino>
    <temptrafego>81</temptrafego>
    <coord>
      <tipo>L</tipo>
      <cpoA>4.42304</cpoA>
      <cpoB>-62.48021</cpoB>
    </coord>
    <altitude>370</altitude>
    <velocidade>450</velocidade>
    <procedimento>TRJ31186</procedimento>
    <niveltrj>370</niveltrj>
    <veltrj>450</veltrj>
  </trafego>

  <trafego nTrf="86">
    <designador>B763</designador>
    <ssr>7564</ssr>
    <indicativo>CLX455</indicativo>
    <origem>SBEG</origem>
    <destino>SPIM</destino>
    <temptrafego>82</temptrafego>
    <coord>
      <tipo>L</tipo>
      <cpoA>-3.10637</cpoA>
      <cpoB>-60.40031</cpoB>
    </coord>
    <altitude>130</altitude>
    <velocidade>300</velocidade>
    <procedimento>TRJ32104</procedimento>
    <niveltrj>340</niveltrj>
    <veltrj>460</veltrj>
  </trafego>

  <trafego nTrf="87">
    <designador>E190</designador>
    <ssr>4201</ssr>
    <indicativo>AZU4276</indicativo>
    <origem>SBEG</origem>
    <destino>SBKP</destino>
    <temptrafego>85</temptrafego>
    <coord>
      <tipo>L</tipo>
      <cpoA>-3.34885</cpoA>
      <cpoB>-59.92989</cpoB>
    </coord>
    <altitude>120</altitude>
    <velocidade>250</velocidade>
    <procedimento>TRJ32101</procedimento>
    <niveltrj>390</niveltrj>
    <veltrj>440</veltrj>
  </trafego>
</trafegos>

