<?xml version='1.0' encoding='UTF-8'?>
<!DOCTYPE trafegos>
<trafegos VERSION="0001" CODE="1961" FORMAT="NEWTON">

  <trafego nTrf="1">
    <designador>LR55</designador>
    <ssr>6301</ssr>
    <indicativo>PRLJC</indicativo>
    <origem>SBEG</origem>
    <destino>SBPV</destino>
    <temptrafego>0</temptrafego>
    <procedimento>SUB4023</procedimento>
  </trafego>

  <trafego nTrf="2">
    <designador>B707</designador>
    <ssr>6302</ssr>
    <indicativo>SKC9070</indicativo>
    <origem>SBEG</origem>
    <destino>SBKP</destino>
    <temptrafego>3</temptrafego>
    <procedimento>SUB4015</procedimento>
  </trafego>

  <trafego nTrf="3">
    <designador>MD11</designador>
    <ssr>6303</ssr>
    <indicativo>VLO9090</indicativo>
    <origem>SBEG</origem>
    <destino>KMIA</destino>
    <temptrafego>7</temptrafego>
    <procedimento>SUB4028</procedimento>
  </trafego>

  <trafego nTrf="4">
    <designador>E110</designador>
    <ssr>6304</ssr>
    <indicativo>PTJMB</indicativo>
    <origem>SBEG</origem>
    <destino>SBTF</destino>
    <temptrafego>11</temptrafego>
    <procedimento>SUB4020</procedimento>
  </trafego>

  <trafego nTrf="5">
    <designador>E120</designador>
    <ssr>6305</ssr>
    <indicativo>COBRA15</indicativo>
    <origem>SBMN</origem>
    <destino>SBBV</destino>
    <temptrafego>15</temptrafego>
    <procedimento>SUB4030</procedimento>
  </trafego>

  <trafego nTrf="6">
    <designador>B737</designador>
    <ssr>6306</ssr>
    <indicativo>GLO1867</indicativo>
    <origem>SBEG</origem>
    <destino>SBBR</destino>
    <temptrafego>17</temptrafego>
    <procedimento>SUB4016</procedimento>
  </trafego>

  <trafego nTrf="7">
    <designador>E120</designador>
    <ssr>6307</ssr>
    <indicativo>TIB5721</indicativo>
    <origem>SBEG</origem>
    <destino>SWPI</destino>
    <temptrafego>20</temptrafego>
    <procedimento>SUB4019</procedimento>
  </trafego>

  <trafego nTrf="8">
    <designador>R99</designador>
    <ssr>6310</ssr>
    <indicativo>GUARD05</indicativo>
    <origem>SBMN</origem>
    <destino>SBBR</destino>
    <temptrafego>25</temptrafego>
    <procedimento>SUB4006</procedimento>
  </trafego>

  <trafego nTrf="9">
    <designador>LR35</designador>
    <ssr>6311</ssr>
    <indicativo>PTLXO</indicativo>
    <origem>SBEG</origem>
    <destino>SVMI</destino>
    <temptrafego>30</temptrafego>
    <procedimento>SUB4038</procedimento>
  </trafego>

  <trafego nTrf="10">
    <designador>C115</designador>
    <ssr>6312</ssr>
    <indicativo>ARARA02</indicativo>
    <origem>SBMN</origem>
    <destino>SBUA</destino>
    <temptrafego>34</temptrafego>
    <procedimento>SUB4032</procedimento>
  </trafego>

  <trafego nTrf="11">
    <designador>DC10</designador>
    <ssr>6313</ssr>
    <indicativo>VLO9092</indicativo>
    <origem>SBEG</origem>
    <destino>SBGR</destino>
    <temptrafego>38</temptrafego>
    <procedimento>SUB4015</procedimento>
  </trafego>

  <trafego nTrf="12">
    <designador>A320</designador>
    <ssr>6314</ssr>
    <indicativo>TAM3809</indicativo>
    <origem>SBEG</origem>
    <destino>SBFZ</destino>
    <temptrafego>41</temptrafego>
    <procedimento>SUB4106</procedimento>
  </trafego>
</trafegos>

