<?xml version='1.0' encoding='UTF-8'?>
<!DOCTYPE trafegos>
<trafegos VERSION="0001" CODE="1961" FORMAT="NEWTON">

  <trafego nTrf="1">
    <designador>AT42</designador>
    <ssr>5112</ssr>
    <indicativo>TIB5515</indicativo>
    <origem>SBRF</origem>
    <destino>SBAR</destino>
    <temptrafego>0</temptrafego>
    <altitude>160</altitude>
    <velocidade>260</velocidade>
    <procedimento>SUB72070</procedimento>
  </trafego>

  <trafego nTrf="2">
    <designador>PA31</designador>
    <ssr>237</ssr>
    <indicativo>PTEFY</indicativo>
    <origem>SBJP</origem>
    <destino>SBRF</destino>
    <temptrafego>4</temptrafego>
    <coord>
      <tipo>L</tipo>
      <cpoA>-8.1365</cpoA>
      <cpoB>-34.76078</cpoB>
    </coord>
    <altitude>30</altitude>
    <velocidade>165</velocidade>
    <proa>184</proa>
  </trafego>

  <trafego nTrf="3">
    <designador>B733</designador>
    <ssr>5117</ssr>
    <indicativo>WEB6757</indicativo>
    <origem>SBRF</origem>
    <destino>SBGR</destino>
    <temptrafego>0</temptrafego>
    <altitude>360</altitude>
    <velocidade>460</velocidade>
    <procedimento>SUB72001</procedimento>
  </trafego>

  <trafego nTrf="4">
    <designador>PA31</designador>
    <ssr>5074</ssr>
    <indicativo>PTESF</indicativo>
    <origem>SBMO</origem>
    <destino>SBRF</destino>
    <temptrafego>0</temptrafego>
    <coord>
      <tipo>L</tipo>
      <cpoA>-8.38125</cpoA>
      <cpoB>-35.26419</cpoB>
    </coord>
    <altitude>50</altitude>
    <velocidade>160</velocidade>
    <proa>60</proa>
  </trafego>

  <trafego nTrf="5">
    <designador>C650</designador>
    <ssr>4434</ssr>
    <indicativo>PREMS</indicativo>
    <origem>SBBE</origem>
    <destino>SBRF</destino>
    <temptrafego>0</temptrafego>
    <coord>
      <tipo>L</tipo>
      <cpoA>-7.85253</cpoA>
      <cpoB>-35.23185</cpoB>
    </coord>
    <altitude>120</altitude>
    <velocidade>410</velocidade>
    <proa>133</proa>
  </trafego>

  <trafego nTrf="6">
    <designador>F100</designador>
    <ssr>5130</ssr>
    <indicativo>ONE6310</indicativo>
    <origem>SBSV</origem>
    <destino>SBRF</destino>
    <temptrafego>0</temptrafego>
    <coord>
      <tipo>L</tipo>
      <cpoA>-8.73697</cpoA>
      <cpoB>-35.92668</cpoB>
    </coord>
    <altitude>200</altitude>
    <velocidade>400</velocidade>
    <procedimento>TRJ720005</procedimento>
  </trafego>

  <trafego nTrf="7">
    <designador>B738</designador>
    <ssr>5141</ssr>
    <indicativo>GLO1643</indicativo>
    <origem>SBFZ</origem>
    <destino>SBRF</destino>
    <temptrafego>0</temptrafego>
    <coord>
      <tipo>L</tipo>
      <cpoA>-6.39407</cpoA>
      <cpoB>-35.49348</cpoB>
    </coord>
    <altitude>250</altitude>
    <velocidade>440</velocidade>
    <procedimento>TRJ720001</procedimento>
  </trafego>

  <trafego nTrf="8">
    <designador>E110</designador>
    <ssr>5101</ssr>
    <indicativo>FAB2304</indicativo>
    <origem>SBFN</origem>
    <destino>SBRF</destino>
    <temptrafego>0</temptrafego>
    <coord>
      <tipo>L</tipo>
      <cpoA>-7.43486</cpoA>
      <cpoB>-33.99622</cpoB>
    </coord>
    <altitude>100</altitude>
    <velocidade>200</velocidade>
    <proa>233</proa>
  </trafego>

  <trafego nTrf="9">
    <designador>E190</designador>
    <ssr>4352</ssr>
    <indicativo>AZU4146</indicativo>
    <origem>SBKP</origem>
    <destino>SBRF</destino>
    <temptrafego>0</temptrafego>
    <coord>
      <tipo>L</tipo>
      <cpoA>-9.68057</cpoA>
      <cpoB>-37.4971</cpoB>
    </coord>
    <altitude>330</altitude>
    <velocidade>460</velocidade>
    <proa>60</proa>
  </trafego>

  <trafego nTrf="10">
    <designador>B738</designador>
    <ssr>4454</ssr>
    <indicativo>GLO1810</indicativo>
    <origem>SBBR</origem>
    <destino>SBRF</destino>
    <temptrafego>0</temptrafego>
    <coord>
      <tipo>L</tipo>
      <cpoA>-8.57943</cpoA>
      <cpoB>-37.72389</cpoB>
    </coord>
    <altitude>370</altitude>
    <velocidade>480</velocidade>
    <proa>80</proa>
  </trafego>

  <trafego nTrf="11">
    <designador>A340</designador>
    <ssr>5221</ssr>
    <indicativo>TAP152</indicativo>
    <origem>LPPT</origem>
    <destino>SBRF</destino>
    <temptrafego>0</temptrafego>
    <coord>
      <tipo>L</tipo>
      <cpoA>-5.90833</cpoA>
      <cpoB>-35.24867</cpoB>
    </coord>
    <altitude>360</altitude>
    <velocidade>480</velocidade>
    <proa>194</proa>
  </trafego>

  <trafego nTrf="12">
    <designador>PA32</designador>
    <ssr>5575</ssr>
    <indicativo>PTVFS</indicativo>
    <origem>SBJP</origem>
    <destino>SBRF</destino>
    <temptrafego>4</temptrafego>
    <altitude>60</altitude>
    <velocidade>125</velocidade>
    <procedimento>SUB72068</procedimento>
  </trafego>

  <trafego nTrf="13">
    <designador>B738</designador>
    <ssr>5062</ssr>
    <indicativo>GLO1260</indicativo>
    <origem>SBRF</origem>
    <destino>SBFZ</destino>
    <temptrafego>5</temptrafego>
    <altitude>380</altitude>
    <velocidade>480</velocidade>
    <procedimento>SUB72007</procedimento>
  </trafego>

  <trafego nTrf="14">
    <designador>B733</designador>
    <ssr>3701</ssr>
    <indicativo>GLO1818</indicativo>
    <origem>SBGL</origem>
    <destino>SBRF</destino>
    <temptrafego>5</temptrafego>
    <coord>
      <tipo>L</tipo>
      <cpoA>-10.98167</cpoA>
      <cpoB>-37.07133</cpoB>
    </coord>
    <altitude>390</altitude>
    <velocidade>480</velocidade>
    <proa>60</proa>
  </trafego>

  <trafego nTrf="15">
    <designador>A320</designador>
    <ssr>4522</ssr>
    <indicativo>TAM3150</indicativo>
    <origem>SBBR</origem>
    <destino>SBRF</destino>
    <temptrafego>4</temptrafego>
    <coord>
      <tipo>L</tipo>
      <cpoA>-9.51683</cpoA>
      <cpoB>-37.14767</cpoB>
    </coord>
    <altitude>410</altitude>
    <velocidade>480</velocidade>
    <proa>80</proa>
  </trafego>

  <trafego nTrf="16">
    <designador>A320</designador>
    <ssr>5042</ssr>
    <indicativo>TAM3893</indicativo>
    <origem>SBFZ</origem>
    <destino>SBRF</destino>
    <temptrafego>7</temptrafego>
    <coord>
      <tipo>L</tipo>
      <cpoA>-5.19733</cpoA>
      <cpoB>-37.3645</cpoB>
    </coord>
    <altitude>370</altitude>
    <velocidade>460</velocidade>
    <proa>162</proa>
  </trafego>

  <trafego nTrf="17">
    <designador>PA32</designador>
    <ssr>225</ssr>
    <indicativo>PTDPD</indicativo>
    <origem>SBRF</origem>
    <destino>SBMO</destino>
    <temptrafego>8</temptrafego>
    <altitude>80</altitude>
    <velocidade>125</velocidade>
    <procedimento>SUB72077</procedimento>
  </trafego>

  <trafego nTrf="18">
    <designador>AT42</designador>
    <ssr>5053</ssr>
    <indicativo>TIB5519</indicativo>
    <origem>SBFN</origem>
    <destino>SBRF</destino>
    <temptrafego>10</temptrafego>
    <coord>
      <tipo>L</tipo>
      <cpoA>-7.23439</cpoA>
      <cpoB>-33.73019</cpoB>
    </coord>
    <altitude>160</altitude>
    <velocidade>240</velocidade>
    <proa>233</proa>
  </trafego>

  <trafego nTrf="19">
    <designador>B738</designador>
    <ssr>3775</ssr>
    <indicativo>GLO1348</indicativo>
    <origem>SBGL</origem>
    <destino>SBRF</destino>
    <temptrafego>13</temptrafego>
    <coord>
      <tipo>L</tipo>
      <cpoA>-10.98167</cpoA>
      <cpoB>-37.07133</cpoB>
    </coord>
    <altitude>410</altitude>
    <velocidade>448</velocidade>
    <proa>60</proa>
  </trafego>

  <trafego nTrf="20">
    <designador>B738</designador>
    <ssr>4334</ssr>
    <indicativo>GLO1210</indicativo>
    <origem>SBBR</origem>
    <destino>SBRF</destino>
    <temptrafego>15</temptrafego>
    <coord>
      <tipo>L</tipo>
      <cpoA>-9.51683</cpoA>
      <cpoB>-37.14767</cpoB>
    </coord>
    <altitude>390</altitude>
    <velocidade>480</velocidade>
    <proa>80</proa>
  </trafego>

  <trafego nTrf="21">
    <designador>A320</designador>
    <ssr>3220</ssr>
    <indicativo>TAM3158</indicativo>
    <origem>SBGL</origem>
    <destino>SBRF</destino>
    <temptrafego>18</temptrafego>
    <coord>
      <tipo>L</tipo>
      <cpoA>-10.98167</cpoA>
      <cpoB>-37.07133</cpoB>
    </coord>
    <altitude>390</altitude>
    <velocidade>450</velocidade>
    <proa>60</proa>
  </trafego>

  <trafego nTrf="22">
    <designador>E190</designador>
    <ssr>4362</ssr>
    <indicativo>AZU4151</indicativo>
    <origem>SBKP</origem>
    <destino>SBRF</destino>
    <temptrafego>20</temptrafego>
    <coord>
      <tipo>L</tipo>
      <cpoA>-10.98167</cpoA>
      <cpoB>-37.07133</cpoB>
    </coord>
    <altitude>350</altitude>
    <velocidade>455</velocidade>
    <proa>60</proa>
  </trafego>

  <trafego nTrf="23">
    <designador>A320</designador>
    <ssr>5034</ssr>
    <indicativo>TAM3305</indicativo>
    <origem>SBSV</origem>
    <destino>SBRF</destino>
    <temptrafego>23</temptrafego>
    <coord>
      <tipo>L</tipo>
      <cpoA>-10.98167</cpoA>
      <cpoB>-37.07133</cpoB>
    </coord>
    <altitude>330</altitude>
    <velocidade>460</velocidade>
    <proa>60</proa>
  </trafego>

  <trafego nTrf="24">
    <designador>B737</designador>
    <ssr>5020</ssr>
    <indicativo>GLO1976</indicativo>
    <origem>SBRF</origem>
    <destino>SBPL</destino>
    <temptrafego>45</temptrafego>
    <altitude>360</altitude>
    <velocidade>480</velocidade>
    <procedimento>SUB72081</procedimento>
  </trafego>

  <trafego nTrf="25">
    <designador>B738</designador>
    <ssr>5052</ssr>
    <indicativo>GLO1212</indicativo>
    <origem>SBRF</origem>
    <destino>SBNT</destino>
    <temptrafego>48</temptrafego>
    <altitude>190</altitude>
    <velocidade>400</velocidade>
    <procedimento>SUB72094</procedimento>
  </trafego>

  <trafego nTrf="26">
    <designador>A320</designador>
    <ssr>5036</ssr>
    <indicativo>TAM3600</indicativo>
    <origem>SBSV</origem>
    <destino>SBJP</destino>
    <temptrafego>28</temptrafego>
    <coord>
      <tipo>L</tipo>
      <cpoA>-10.98167</cpoA>
      <cpoB>-37.07133</cpoB>
    </coord>
    <altitude>370</altitude>
    <velocidade>480</velocidade>
    <proa>53</proa>
  </trafego>

  <trafego nTrf="27">
    <designador>PA34</designador>
    <ssr>5057</ssr>
    <indicativo>PTVEK</indicativo>
    <origem>SNAE</origem>
    <destino>SBRF</destino>
    <temptrafego>50</temptrafego>
    <coord>
      <tipo>L</tipo>
      <cpoA>-7.84728</cpoA>
      <cpoB>-36.56757</cpoB>
    </coord>
    <altitude>75</altitude>
    <velocidade>180</velocidade>
    <proa>110</proa>
  </trafego>

  <trafego nTrf="28">
    <designador>A320</designador>
    <ssr>5055</ssr>
    <indicativo>TAM3156</indicativo>
    <origem>SBRF</origem>
    <destino>SBJP</destino>
    <temptrafego>50</temptrafego>
    <altitude>110</altitude>
    <velocidade>400</velocidade>
    <procedimento>SUB72090</procedimento>
  </trafego>

  <trafego nTrf="29">
    <designador>B738</designador>
    <ssr>4435</ssr>
    <indicativo>GLO1768</indicativo>
    <origem>SBGR</origem>
    <destino>SBRF</destino>
    <temptrafego>28</temptrafego>
    <coord>
      <tipo>L</tipo>
      <cpoA>-10.98167</cpoA>
      <cpoB>-37.07133</cpoB>
    </coord>
    <altitude>390</altitude>
    <velocidade>480</velocidade>
    <proa>60</proa>
  </trafego>

  <trafego nTrf="30">
    <designador>B738</designador>
    <ssr>4446</ssr>
    <indicativo>GLO1688</indicativo>
    <origem>SBKP</origem>
    <destino>SBRF</destino>
    <temptrafego>31</temptrafego>
    <coord>
      <tipo>L</tipo>
      <cpoA>-10.98167</cpoA>
      <cpoB>-37.07133</cpoB>
    </coord>
    <altitude>370</altitude>
    <velocidade>440</velocidade>
    <proa>60</proa>
  </trafego>

  <trafego nTrf="31">
    <designador>E190</designador>
    <ssr>5572</ssr>
    <indicativo>AZU4152</indicativo>
    <origem>SBRF</origem>
    <destino>SBKP</destino>
    <temptrafego>57</temptrafego>
    <altitude>360</altitude>
    <velocidade>460</velocidade>
    <procedimento>SUB72080</procedimento>
  </trafego>

  <trafego nTrf="32">
    <designador>A320</designador>
    <ssr>5060</ssr>
    <indicativo>TAM3601</indicativo>
    <origem>SBJP</origem>
    <destino>SBSV</destino>
    <temptrafego>55</temptrafego>
    <altitude>360</altitude>
    <velocidade>470</velocidade>
    <procedimento>SUB72068</procedimento>
  </trafego>

  <trafego nTrf="33">
    <designador>A321</designador>
    <ssr>4436</ssr>
    <indicativo>TAM3506</indicativo>
    <origem>SBGR</origem>
    <destino>SBRF</destino>
    <temptrafego>35</temptrafego>
    <coord>
      <tipo>L</tipo>
      <cpoA>-10.98167</cpoA>
      <cpoB>-37.07133</cpoB>
    </coord>
    <altitude>350</altitude>
    <velocidade>480</velocidade>
    <proa>60</proa>
  </trafego>

  <trafego nTrf="34">
    <designador>B738</designador>
    <ssr>4462</ssr>
    <indicativo>GLO1852</indicativo>
    <origem>SBBR</origem>
    <destino>SBRF</destino>
    <temptrafego>38</temptrafego>
    <coord>
      <tipo>L</tipo>
      <cpoA>-9.51683</cpoA>
      <cpoB>-37.14767</cpoB>
    </coord>
    <altitude>370</altitude>
    <velocidade>480</velocidade>
    <proa>80</proa>
  </trafego>

  <trafego nTrf="35">
    <designador>B738</designador>
    <ssr>5040</ssr>
    <indicativo>GLO1896</indicativo>
    <origem>SBSV</origem>
    <destino>SBRF</destino>
    <temptrafego>48</temptrafego>
    <coord>
      <tipo>L</tipo>
      <cpoA>-10.98167</cpoA>
      <cpoB>-37.07133</cpoB>
    </coord>
    <altitude>370</altitude>
    <velocidade>470</velocidade>
    <proa>80</proa>
  </trafego>

  <trafego nTrf="36">
    <designador>A320</designador>
    <ssr>5065</ssr>
    <indicativo>TAM3359</indicativo>
    <origem>SBJP</origem>
    <destino>SBGR</destino>
    <temptrafego>75</temptrafego>
    <altitude>360</altitude>
    <velocidade>480</velocidade>
    <procedimento>SUB72068</procedimento>
  </trafego>

  <trafego nTrf="37">
    <designador>A320</designador>
    <ssr>4456</ssr>
    <indicativo>TAM3358</indicativo>
    <origem>SBGR</origem>
    <destino>SBRF</destino>
    <temptrafego>35</temptrafego>
    <coord>
      <tipo>L</tipo>
      <cpoA>-10.98167</cpoA>
      <cpoB>-37.07133</cpoB>
    </coord>
    <altitude>390</altitude>
    <velocidade>480</velocidade>
    <proa>60</proa>
  </trafego>

  <trafego nTrf="38">
    <designador>B738</designador>
    <ssr>5072</ssr>
    <indicativo>GLO1769</indicativo>
    <origem>SBRF</origem>
    <destino>SBBR</destino>
    <temptrafego>70</temptrafego>
    <altitude>360</altitude>
    <velocidade>480</velocidade>
    <procedimento>SUB72006</procedimento>
  </trafego>

  <trafego nTrf="39">
    <designador>A321</designador>
    <ssr>5075</ssr>
    <indicativo>TAM3501</indicativo>
    <origem>SBRF</origem>
    <destino>SBGR</destino>
    <temptrafego>72</temptrafego>
    <altitude>360</altitude>
    <velocidade>460</velocidade>
    <procedimento>SUB72001</procedimento>
  </trafego>

  <trafego nTrf="40">
    <designador>B738</designador>
    <ssr>5113</ssr>
    <indicativo>GLO1689</indicativo>
    <origem>SBRF</origem>
    <destino>SBKP</destino>
    <temptrafego>75</temptrafego>
    <altitude>380</altitude>
    <velocidade>480</velocidade>
    <procedimento>SUB72080</procedimento>
  </trafego>

  <trafego nTrf="41">
    <designador>B738</designador>
    <ssr>5115</ssr>
    <indicativo>GLO1203</indicativo>
    <origem>SBNT</origem>
    <destino>SBRF</destino>
    <temptrafego>73</temptrafego>
    <coord>
      <tipo>L</tipo>
      <cpoA>-6.57979</cpoA>
      <cpoB>-35.02491</cpoB>
    </coord>
    <altitude>220</altitude>
    <velocidade>420</velocidade>
    <proa>194</proa>
  </trafego>

  <trafego nTrf="42">
    <designador>B738</designador>
    <ssr>3371</ssr>
    <indicativo>GLO1744</indicativo>
    <origem>SBGL</origem>
    <destino>SBRF</destino>
    <temptrafego>53</temptrafego>
    <coord>
      <tipo>L</tipo>
      <cpoA>-10.98167</cpoA>
      <cpoB>-37.07133</cpoB>
    </coord>
    <altitude>390</altitude>
    <velocidade>450</velocidade>
    <proa>60</proa>
  </trafego>

  <trafego nTrf="43">
    <designador>A320</designador>
    <ssr>5123</ssr>
    <indicativo>TAM3153</indicativo>
    <origem>SBRF</origem>
    <destino>SBBR</destino>
    <temptrafego>80</temptrafego>
    <altitude>340</altitude>
    <velocidade>460</velocidade>
    <procedimento>SUB72081</procedimento>
  </trafego>

  <trafego nTrf="44">
    <designador>A320</designador>
    <ssr>5125</ssr>
    <indicativo>TAM3159</indicativo>
    <origem>SBJP</origem>
    <destino>SBRF</destino>
    <temptrafego>76</temptrafego>
    <altitude>110</altitude>
    <velocidade>400</velocidade>
    <procedimento>SUB72068</procedimento>
  </trafego>

  <trafego nTrf="45">
    <designador>B738</designador>
    <ssr>5144</ssr>
    <indicativo>GLO1729</indicativo>
    <origem>SBRF</origem>
    <destino>SBGR</destino>
    <temptrafego>85</temptrafego>
    <altitude>380</altitude>
    <velocidade>480</velocidade>
    <procedimento>SUB72080</procedimento>
  </trafego>

  <trafego nTrf="46">
    <designador>E120</designador>
    <ssr>5134</ssr>
    <indicativo>FAB2020</indicativo>
    <origem>SBMO</origem>
    <destino>SBRF</destino>
    <temptrafego>80</temptrafego>
    <coord>
      <tipo>L</tipo>
      <cpoA>-9.00406</cpoA>
      <cpoB>-35.64936</cpoB>
    </coord>
    <altitude>150</altitude>
    <velocidade>260</velocidade>
    <proa>60</proa>
  </trafego>

  <trafego nTrf="47">
    <designador>B733</designador>
    <ssr>5151</ssr>
    <indicativo>WEB6709</indicativo>
    <origem>SBRF</origem>
    <destino>SBSV</destino>
    <temptrafego>82</temptrafego>
    <altitude>340</altitude>
    <velocidade>460</velocidade>
    <procedimento>SUB72001</procedimento>
  </trafego>

  <trafego nTrf="48">
    <designador>A320</designador>
    <ssr>5161</ssr>
    <indicativo>TAM3503</indicativo>
    <origem>SBRF</origem>
    <destino>SBGR</destino>
    <temptrafego>87</temptrafego>
    <altitude>360</altitude>
    <velocidade>460</velocidade>
    <procedimento>SUB72080</procedimento>
  </trafego>

  <trafego nTrf="49">
    <designador>B738</designador>
    <ssr>5160</ssr>
    <indicativo>GLO1205</indicativo>
    <origem>SBRF</origem>
    <destino>SBBR</destino>
    <temptrafego>92</temptrafego>
    <altitude>380</altitude>
    <velocidade>480</velocidade>
    <procedimento>SUB72081</procedimento>
  </trafego>

  <trafego nTrf="50">
    <designador>BE58</designador>
    <ssr>5171</ssr>
    <indicativo>PTWNM</indicativo>
    <origem>SBRF</origem>
    <destino>SBKG</destino>
    <temptrafego>214</temptrafego>
    <altitude>60</altitude>
    <velocidade>140</velocidade>
    <procedimento>SUB72076</procedimento>
  </trafego>

  <trafego nTrf="51">
    <designador>BE58</designador>
    <ssr>5172</ssr>
    <indicativo>PTICU</indicativo>
    <origem>SBRF</origem>
    <destino>SNAE</destino>
    <temptrafego>216</temptrafego>
    <altitude>60</altitude>
    <velocidade>140</velocidade>
    <procedimento>SUB72074</procedimento>
  </trafego>

  <trafego nTrf="52">
    <designador>B738</designador>
    <ssr>5152</ssr>
    <indicativo>GLO1349</indicativo>
    <origem>SBRF</origem>
    <destino>SBGL</destino>
    <temptrafego>99</temptrafego>
    <altitude>380</altitude>
    <velocidade>480</velocidade>
    <procedimento>SUB72080</procedimento>
  </trafego>

  <trafego nTrf="53">
    <designador>A320</designador>
    <ssr>5162</ssr>
    <indicativo>TAM3865</indicativo>
    <origem>SBRF</origem>
    <destino>SBBR</destino>
    <temptrafego>103</temptrafego>
    <altitude>360</altitude>
    <velocidade>470</velocidade>
    <procedimento>SUB72081</procedimento>
  </trafego>

  <trafego nTrf="54">
    <designador>PA31</designador>
    <ssr>5402</ssr>
    <indicativo>PTESO</indicativo>
    <origem>SBRF</origem>
    <destino>SBMO</destino>
    <temptrafego>107</temptrafego>
    <altitude>60</altitude>
    <velocidade>180</velocidade>
    <procedimento>SUB72077</procedimento>
  </trafego>

  <trafego nTrf="55">
    <designador>PA31</designador>
    <ssr>315</ssr>
    <indicativo>PTENO</indicativo>
    <origem>SBRF</origem>
    <destino>SBNT</destino>
    <temptrafego>107</temptrafego>
    <altitude>80</altitude>
    <velocidade>180</velocidade>
    <procedimento>SUB72087</procedimento>
  </trafego>

  <trafego nTrf="56">
    <designador>PA31</designador>
    <ssr>5403</ssr>
    <indicativo>PTEFR</indicativo>
    <origem>SBRF</origem>
    <destino>SBJP</destino>
    <temptrafego>229</temptrafego>
    <altitude>50</altitude>
    <velocidade>130</velocidade>
    <procedimento>SUB72087</procedimento>
  </trafego>

  <trafego nTrf="57">
    <designador>A320</designador>
    <ssr>5154</ssr>
    <indicativo>TAM3890</indicativo>
    <origem>SBSV</origem>
    <destino>SBRF</destino>
    <temptrafego>93</temptrafego>
    <coord>
      <tipo>L</tipo>
      <cpoA>-10.98167</cpoA>
      <cpoB>-37.07133</cpoB>
    </coord>
    <altitude>330</altitude>
    <velocidade>460</velocidade>
    <proa>60</proa>
  </trafego>

  <trafego nTrf="58">
    <designador>F100</designador>
    <ssr>5150</ssr>
    <indicativo>ONE6311</indicativo>
    <origem>SBPL</origem>
    <destino>SBRF</destino>
    <temptrafego>95</temptrafego>
    <coord>
      <tipo>L</tipo>
      <cpoA>-7.55806</cpoA>
      <cpoB>-38.20781</cpoB>
    </coord>
    <altitude>350</altitude>
    <velocidade>400</velocidade>
    <proa>100</proa>
  </trafego>

  <trafego nTrf="59">
    <designador>PA34</designador>
    <ssr>5177</ssr>
    <indicativo>PTVSU</indicativo>
    <origem>SBMO</origem>
    <destino>SBRF</destino>
    <temptrafego>112</temptrafego>
    <coord>
      <tipo>L</tipo>
      <cpoA>-8.8325</cpoA>
      <cpoB>-35.36383</cpoB>
    </coord>
    <altitude>70</altitude>
    <velocidade>160</velocidade>
    <proa>60</proa>
  </trafego>

  <trafego nTrf="60">
    <designador>B737</designador>
    <ssr>5167</ssr>
    <indicativo>GLO1977</indicativo>
    <origem>SBPL</origem>
    <destino>SBRF</destino>
    <temptrafego>98</temptrafego>
    <coord>
      <tipo>L</tipo>
      <cpoA>-7.55806</cpoA>
      <cpoB>-38.20781</cpoB>
    </coord>
    <altitude>350</altitude>
    <velocidade>480</velocidade>
    <proa>100</proa>
  </trafego>

  <trafego nTrf="61">
    <designador>A320</designador>
    <ssr>5407</ssr>
    <indicativo>TAM3515</indicativo>
    <origem>SBFZ</origem>
    <destino>SBRF</destino>
    <temptrafego>95</temptrafego>
    <coord>
      <tipo>L</tipo>
      <cpoA>-5.19733</cpoA>
      <cpoB>-37.3645</cpoB>
    </coord>
    <altitude>370</altitude>
    <velocidade>470</velocidade>
    <proa>162</proa>
  </trafego>

  <trafego nTrf="62">
    <designador>E110</designador>
    <ssr>5426</ssr>
    <indicativo>PASTOR04</indicativo>
    <origem>SBMO</origem>
    <destino>SBRF</destino>
    <temptrafego>119</temptrafego>
    <coord>
      <tipo>L</tipo>
      <cpoA>-8.8325</cpoA>
      <cpoB>-35.36383</cpoB>
    </coord>
    <altitude>70</altitude>
    <velocidade>190</velocidade>
    <proa>60</proa>
  </trafego>

  <trafego nTrf="63">
    <designador>A320</designador>
    <ssr>5420</ssr>
    <indicativo>TAM3304</indicativo>
    <origem>SBRF</origem>
    <destino>SBSV</destino>
    <temptrafego>115</temptrafego>
    <altitude>340</altitude>
    <velocidade>460</velocidade>
    <procedimento>SUB72080</procedimento>
  </trafego>

  <trafego nTrf="64">
    <designador>E120</designador>
    <ssr>5425</ssr>
    <indicativo>FAB2121</indicativo>
    <origem>SBRF</origem>
    <destino>SBSV</destino>
    <temptrafego>117</temptrafego>
    <altitude>260</altitude>
    <velocidade>320</velocidade>
    <procedimento>SUB72001</procedimento>
  </trafego>

  <trafego nTrf="65">
    <designador>B738</designador>
    <ssr>5555</ssr>
    <indicativo>GLO1642</indicativo>
    <origem>SBSV</origem>
    <destino>SBRF</destino>
    <temptrafego>108</temptrafego>
    <coord>
      <tipo>L</tipo>
      <cpoA>-10.98167</cpoA>
      <cpoB>-37.07133</cpoB>
    </coord>
    <altitude>350</altitude>
    <velocidade>470</velocidade>
    <proa>60</proa>
  </trafego>

  <trafego nTrf="66">
    <designador>F100</designador>
    <ssr>5442</ssr>
    <indicativo>ONE6313</indicativo>
    <origem>SBRF</origem>
    <destino>SBSV</destino>
    <temptrafego>125</temptrafego>
    <altitude>320</altitude>
    <velocidade>440</velocidade>
    <procedimento>SUB72001</procedimento>
  </trafego>

  <trafego nTrf="67">
    <designador>PA32</designador>
    <ssr>317</ssr>
    <indicativo>PTVFO</indicativo>
    <origem>SBRF</origem>
    <destino>SBNT</destino>
    <temptrafego>130</temptrafego>
    <altitude>80</altitude>
    <velocidade>125</velocidade>
    <procedimento>SUB72087</procedimento>
  </trafego>

  <trafego nTrf="68">
    <designador>C525</designador>
    <ssr>5454</ssr>
    <indicativo>PRTOP</indicativo>
    <origem>SBRF</origem>
    <destino>SBCF</destino>
    <temptrafego>134</temptrafego>
    <altitude>300</altitude>
    <velocidade>360</velocidade>
    <procedimento>SUB72001</procedimento>
  </trafego>

  <trafego nTrf="69">
    <designador>PA32</designador>
    <ssr>5451</ssr>
    <indicativo>PTDPO</indicativo>
    <origem>SBRF</origem>
    <destino>SBMO</destino>
    <temptrafego>136</temptrafego>
    <altitude>60</altitude>
    <velocidade>125</velocidade>
    <procedimento>SUB72077</procedimento>
  </trafego>

  <trafego nTrf="70">
    <designador>A320</designador>
    <ssr>5456</ssr>
    <indicativo>TAM3892</indicativo>
    <origem>SBRF</origem>
    <destino>SBFZ</destino>
    <temptrafego>140</temptrafego>
    <altitude>340</altitude>
    <velocidade>480</velocidade>
    <procedimento>SUB72007</procedimento>
  </trafego>

  <trafego nTrf="71">
    <designador>B722</designador>
    <ssr>5424</ssr>
    <indicativo>TTL9911</indicativo>
    <origem>SBSV</origem>
    <destino>SBRF</destino>
    <temptrafego>113</temptrafego>
    <coord>
      <tipo>L</tipo>
      <cpoA>-10.98167</cpoA>
      <cpoB>-37.07133</cpoB>
    </coord>
    <altitude>290</altitude>
    <velocidade>480</velocidade>
    <proa>60</proa>
  </trafego>

  <trafego nTrf="72">
    <designador>PA34</designador>
    <ssr>5436</ssr>
    <indicativo>PTVED</indicativo>
    <origem>SNTS</origem>
    <destino>SBJP</destino>
    <temptrafego>138</temptrafego>
    <coord>
      <tipo>L</tipo>
      <cpoA>-6.71226</cpoA>
      <cpoB>-35.46268</cpoB>
    </coord>
    <altitude>135</altitude>
    <velocidade>135</velocidade>
    <proa>135</proa>
  </trafego>

  <trafego nTrf="73">
    <designador>B737</designador>
    <ssr>5462</ssr>
    <indicativo>GLO1979</indicativo>
    <origem>SBRF</origem>
    <destino>SBGR</destino>
    <temptrafego>145</temptrafego>
    <altitude>380</altitude>
    <velocidade>480</velocidade>
    <procedimento>SUB72080</procedimento>
  </trafego>

  <trafego nTrf="74">
    <designador>E110</designador>
    <ssr>5473</ssr>
    <indicativo>FAB2306</indicativo>
    <origem>SBRF</origem>
    <destino>SBFN</destino>
    <temptrafego>147</temptrafego>
    <altitude>100</altitude>
    <velocidade>180</velocidade>
    <procedimento>SUB72085</procedimento>
  </trafego>

  <trafego nTrf="75">
    <designador>E110</designador>
    <ssr>236</ssr>
    <indicativo>FAB2240</indicativo>
    <origem>SBRF</origem>
    <destino>SBSV</destino>
    <temptrafego>149</temptrafego>
    <altitude>100</altitude>
    <velocidade>180</velocidade>
    <procedimento>SUB72077</procedimento>
  </trafego>

  <trafego nTrf="76">
    <designador>E190</designador>
    <ssr>5573</ssr>
    <indicativo>AZU4154</indicativo>
    <origem>SBRF</origem>
    <destino>SBKP</destino>
    <temptrafego>147</temptrafego>
    <altitude>340</altitude>
    <velocidade>460</velocidade>
    <procedimento>SUB72080</procedimento>
  </trafego>

  <trafego nTrf="77">
    <designador>A320</designador>
    <ssr>5061</ssr>
    <indicativo>TAM3603</indicativo>
    <origem>SBJP</origem>
    <destino>SBSV</destino>
    <temptrafego>145</temptrafego>
    <altitude>340</altitude>
    <velocidade>470</velocidade>
    <procedimento>SUB72068</procedimento>
  </trafego>

  <trafego nTrf="78">
    <designador>A321</designador>
    <ssr>4437</ssr>
    <indicativo>TAM3508</indicativo>
    <origem>SBGR</origem>
    <destino>SBRF</destino>
    <temptrafego>125</temptrafego>
    <coord>
      <tipo>L</tipo>
      <cpoA>-10.98167</cpoA>
      <cpoB>-37.07133</cpoB>
    </coord>
    <altitude>390</altitude>
    <velocidade>480</velocidade>
    <proa>60</proa>
  </trafego>

  <trafego nTrf="79">
    <designador>B738</designador>
    <ssr>4463</ssr>
    <indicativo>GLO1854</indicativo>
    <origem>SBBR</origem>
    <destino>SBRF</destino>
    <temptrafego>128</temptrafego>
    <coord>
      <tipo>L</tipo>
      <cpoA>-9.51683</cpoA>
      <cpoB>-37.14767</cpoB>
    </coord>
    <altitude>410</altitude>
    <velocidade>480</velocidade>
    <proa>80</proa>
  </trafego>

  <trafego nTrf="80">
    <designador>B737</designador>
    <ssr>5041</ssr>
    <indicativo>GLO1898</indicativo>
    <origem>SBSV</origem>
    <destino>SBJP</destino>
    <temptrafego>138</temptrafego>
    <coord>
      <tipo>L</tipo>
      <cpoA>-10.98167</cpoA>
      <cpoB>-37.07133</cpoB>
    </coord>
    <altitude>310</altitude>
    <velocidade>470</velocidade>
    <proa>60</proa>
  </trafego>

  <trafego nTrf="81">
    <designador>A320</designador>
    <ssr>5332</ssr>
    <indicativo>TAM3364</indicativo>
    <origem>SBFZ</origem>
    <destino>SBRF</destino>
    <temptrafego>150</temptrafego>
    <coord>
      <tipo>L</tipo>
      <cpoA>-6.55248</cpoA>
      <cpoB>-35.44201</cpoB>
    </coord>
    <altitude>370</altitude>
    <velocidade>480</velocidade>
    <proa>162</proa>
  </trafego>

  <trafego nTrf="82">
    <designador>A320</designador>
    <ssr>4670</ssr>
    <indicativo>TAM3524</indicativo>
    <origem>SBGR</origem>
    <destino>SBRF</destino>
    <temptrafego>123</temptrafego>
    <coord>
      <tipo>L</tipo>
      <cpoA>-10.98167</cpoA>
      <cpoB>-37.07133</cpoB>
    </coord>
    <altitude>390</altitude>
    <velocidade>480</velocidade>
    <proa>60</proa>
  </trafego>

  <trafego nTrf="83">
    <designador>E110</designador>
    <ssr>5465</ssr>
    <indicativo>PTSHP</indicativo>
    <origem>SBUF</origem>
    <destino>SBRF</destino>
    <temptrafego>107</temptrafego>
    <coord>
      <tipo>L</tipo>
      <cpoA>-8.10743</cpoA>
      <cpoB>-36.59262</cpoB>
    </coord>
    <altitude>90</altitude>
    <velocidade>200</velocidade>
    <proa>92</proa>
  </trafego>

  <trafego nTrf="84">
    <designador>PA34</designador>
    <ssr>5463</ssr>
    <indicativo>PTVEO</indicativo>
    <origem>SBRF</origem>
    <destino>SBMO</destino>
    <temptrafego>167</temptrafego>
    <altitude>80</altitude>
    <velocidade>180</velocidade>
    <procedimento>SUB72077</procedimento>
  </trafego>

  <trafego nTrf="85">
    <designador>B737</designador>
    <ssr>3752</ssr>
    <indicativo>GLO1660</indicativo>
    <origem>SBGL</origem>
    <destino>SBRF</destino>
    <temptrafego>147</temptrafego>
    <coord>
      <tipo>L</tipo>
      <cpoA>-10.98167</cpoA>
      <cpoB>-37.07133</cpoB>
    </coord>
    <altitude>330</altitude>
    <velocidade>480</velocidade>
    <proa>60</proa>
  </trafego>

  <trafego nTrf="86">
    <designador>E145</designador>
    <ssr>5511</ssr>
    <indicativo>PRPFN</indicativo>
    <origem>SBTE</origem>
    <destino>SBJP</destino>
    <temptrafego>138</temptrafego>
    <coord>
      <tipo>L</tipo>
      <cpoA>-6.77342</cpoA>
      <cpoB>-36.38905</cpoB>
    </coord>
    <altitude>370</altitude>
    <velocidade>410</velocidade>
    <proa>133</proa>
  </trafego>

  <trafego nTrf="87">
    <designador>C525</designador>
    <ssr>402</ssr>
    <indicativo>N9UD</indicativo>
    <origem>SBNT</origem>
    <destino>SBRF</destino>
    <temptrafego>150</temptrafego>
    <coord>
      <tipo>L</tipo>
      <cpoA>-6.903</cpoA>
      <cpoB>-35.1055</cpoB>
    </coord>
    <altitude>220</altitude>
    <velocidade>400</velocidade>
    <proa>194</proa>
  </trafego>

  <trafego nTrf="88">
    <designador>B737</designador>
    <ssr>3753</ssr>
    <indicativo>GLO1662</indicativo>
    <origem>SBGL</origem>
    <destino>SBRF</destino>
    <temptrafego>128</temptrafego>
    <coord>
      <tipo>L</tipo>
      <cpoA>-10.98167</cpoA>
      <cpoB>-37.07133</cpoB>
    </coord>
    <altitude>390</altitude>
    <velocidade>470</velocidade>
    <proa>60</proa>
  </trafego>

  <trafego nTrf="89">
    <designador>A320</designador>
    <ssr>5527</ssr>
    <indicativo>TAM3454</indicativo>
    <origem>SBSV</origem>
    <destino>SBRF</destino>
    <temptrafego>130</temptrafego>
    <coord>
      <tipo>L</tipo>
      <cpoA>-10.98167</cpoA>
      <cpoB>-37.07133</cpoB>
    </coord>
    <altitude>350</altitude>
    <velocidade>480</velocidade>
    <proa>60</proa>
  </trafego>

  <trafego nTrf="90">
    <designador>AT42</designador>
    <ssr>5530</ssr>
    <indicativo>TIB5514</indicativo>
    <origem>SBRF</origem>
    <destino>SBNT</destino>
    <temptrafego>172</temptrafego>
    <altitude>160</altitude>
    <velocidade>200</velocidade>
    <procedimento>SUB72087</procedimento>
  </trafego>

  <trafego nTrf="91">
    <designador>B757</designador>
    <ssr>5553</ssr>
    <indicativo>VLO6514</indicativo>
    <origem>SBRF</origem>
    <destino>SBFZ</destino>
    <temptrafego>175</temptrafego>
    <altitude>360</altitude>
    <velocidade>480</velocidade>
    <procedimento>SUB72007</procedimento>
  </trafego>

  <trafego nTrf="92">
    <designador>BE9L</designador>
    <ssr>5461</ssr>
    <indicativo>PRCMI</indicativo>
    <origem>SBKG</origem>
    <destino>SBJP</destino>
    <temptrafego>173</temptrafego>
    <coord>
      <tipo>L</tipo>
      <cpoA>-7.23831</cpoA>
      <cpoB>-35.36541</cpoB>
    </coord>
    <altitude>70</altitude>
    <velocidade>210</velocidade>
    <proa>100</proa>
  </trafego>

  <trafego nTrf="93">
    <designador>E110</designador>
    <ssr>440</ssr>
    <indicativo>RUMBA22</indicativo>
    <origem>SBFZ</origem>
    <destino>SBRF</destino>
    <temptrafego>174</temptrafego>
    <coord>
      <tipo>L</tipo>
      <cpoA>-7.08861</cpoA>
      <cpoB>-35.43842</cpoB>
    </coord>
    <altitude>130</altitude>
    <velocidade>200</velocidade>
    <proa>155</proa>
  </trafego>

  <trafego nTrf="94">
    <designador>A320</designador>
    <ssr>5560</ssr>
    <indicativo>TAM3083</indicativo>
    <origem>SBRF</origem>
    <destino>SBGL</destino>
    <temptrafego>177</temptrafego>
    <altitude>360</altitude>
    <velocidade>470</velocidade>
    <procedimento>SUB72080</procedimento>
  </trafego>

  <trafego nTrf="95">
    <designador>B757</designador>
    <ssr>5526</ssr>
    <indicativo>AAL980</indicativo>
    <origem>SBSV</origem>
    <destino>SBRF</destino>
    <temptrafego>155</temptrafego>
    <coord>
      <tipo>L</tipo>
      <cpoA>-10.98167</cpoA>
      <cpoB>-37.07133</cpoB>
    </coord>
    <altitude>370</altitude>
    <velocidade>480</velocidade>
    <proa>60</proa>
  </trafego>

  <trafego nTrf="96">
    <designador>LJ35</designador>
    <ssr>4354</ssr>
    <indicativo>CARCARA01</indicativo>
    <origem>SBBR</origem>
    <destino>SBRF</destino>
    <temptrafego>180</temptrafego>
    <coord>
      <tipo>L</tipo>
      <cpoA>-9.51683</cpoA>
      <cpoB>-37.14767</cpoB>
    </coord>
    <altitude>350</altitude>
    <velocidade>440</velocidade>
    <proa>80</proa>
  </trafego>

  <trafego nTrf="97">
    <designador>A320</designador>
    <ssr>5004</ssr>
    <indicativo>TAM3891</indicativo>
    <origem>SBFZ</origem>
    <destino>SBRF</destino>
    <temptrafego>0</temptrafego>
    <coord>
      <tipo>L</tipo>
      <cpoA>-6.86928</cpoA>
      <cpoB>-35.33907</cpoB>
    </coord>
    <altitude>330</altitude>
    <velocidade>480</velocidade>
    <proa>162</proa>
  </trafego>

  <trafego nTrf="98">
    <designador>A343</designador>
    <ssr>5005</ssr>
    <indicativo>IBE6824</indicativo>
    <origem>LEMD</origem>
    <destino>SBRF</destino>
    <temptrafego>0</temptrafego>
    <coord>
      <tipo>L</tipo>
      <cpoA>-7.31617</cpoA>
      <cpoB>-33.87736</cpoB>
    </coord>
    <altitude>360</altitude>
    <velocidade>480</velocidade>
    <proa>232</proa>
  </trafego>

  <trafego nTrf="99">
    <designador>A342</designador>
    <ssr>5006</ssr>
    <indicativo>TAP156</indicativo>
    <origem>LPPT</origem>
    <destino>SBRF</destino>
    <temptrafego>0</temptrafego>
    <coord>
      <tipo>L</tipo>
      <cpoA>-5.58715</cpoA>
      <cpoB>-34.86591</cpoB>
    </coord>
    <altitude>340</altitude>
    <velocidade>480</velocidade>
    <proa>230</proa>
  </trafego>

  <trafego nTrf="100">
    <designador>B738</designador>
    <ssr>5007</ssr>
    <indicativo>GLO1811</indicativo>
    <origem>SBJU</origem>
    <destino>SBRF</destino>
    <temptrafego>0</temptrafego>
    <coord>
      <tipo>L</tipo>
      <cpoA>-7.11419</cpoA>
      <cpoB>-36.02362</cpoB>
    </coord>
    <altitude>330</altitude>
    <velocidade>480</velocidade>
    <proa>133</proa>
  </trafego>

  <trafego nTrf="101">
    <designador>A320</designador>
    <ssr>5110</ssr>
    <indicativo>TAM3342</indicativo>
    <origem>SBBE</origem>
    <destino>SBRF</destino>
    <temptrafego>30</temptrafego>
    <coord>
      <tipo>L</tipo>
      <cpoA>-7.11419</cpoA>
      <cpoB>-36.02362</cpoB>
    </coord>
    <altitude>390</altitude>
    <velocidade>480</velocidade>
    <proa>133</proa>
  </trafego>

  <trafego nTrf="102">
    <designador>LJ60</designador>
    <ssr>5111</ssr>
    <indicativo>PTLLS</indicativo>
    <origem>SBFZ</origem>
    <destino>SBRF</destino>
    <temptrafego>32</temptrafego>
    <coord>
      <tipo>L</tipo>
      <cpoA>-6.55248</cpoA>
      <cpoB>-35.44201</cpoB>
    </coord>
    <altitude>390</altitude>
    <velocidade>460</velocidade>
    <proa>162</proa>
  </trafego>

  <trafego nTrf="103">
    <designador>B737</designador>
    <ssr>5114</ssr>
    <indicativo>GLO1622</indicativo>
    <origem>SBFZ</origem>
    <destino>SBRF</destino>
    <temptrafego>33</temptrafego>
    <coord>
      <tipo>L</tipo>
      <cpoA>-6.55248</cpoA>
      <cpoB>-35.44201</cpoB>
    </coord>
    <altitude>370</altitude>
    <velocidade>480</velocidade>
    <proa>162</proa>
  </trafego>

  <trafego nTrf="104">
    <designador>B738</designador>
    <ssr>5116</ssr>
    <indicativo>GLO1667</indicativo>
    <origem>SBFN</origem>
    <destino>SBRF</destino>
    <temptrafego>10</temptrafego>
    <coord>
      <tipo>L</tipo>
      <cpoA>-3.86</cpoA>
      <cpoB>-32.43</cpoB>
    </coord>
    <altitude>20</altitude>
    <velocidade>210</velocidade>
    <procedimento>TRJ720017</procedimento>
  </trafego>

  <trafego nTrf="105">
    <designador>A340</designador>
    <ssr>5222</ssr>
    <indicativo>APW212</indicativo>
    <origem>KMIA</origem>
    <destino>SBRF</destino>
    <temptrafego>80</temptrafego>
    <coord>
      <tipo>L</tipo>
      <cpoA>-7.0006</cpoA>
      <cpoB>-36.14543</cpoB>
    </coord>
    <altitude>390</altitude>
    <velocidade>480</velocidade>
    <proa>133</proa>
  </trafego>

  <trafego nTrf="106">
    <designador>A343</designador>
    <ssr>5224</ssr>
    <indicativo>AZA675</indicativo>
    <origem>LIRF</origem>
    <destino>SBRF</destino>
    <temptrafego>90</temptrafego>
    <coord>
      <tipo>L</tipo>
      <cpoA>-7.08403</cpoA>
      <cpoB>-33.53066</cpoB>
    </coord>
    <altitude>380</altitude>
    <velocidade>480</velocidade>
    <proa>232</proa>
  </trafego>

  <trafego nTrf="107">
    <designador>C750</designador>
    <ssr>5225</ssr>
    <indicativo>N356AW</indicativo>
    <origem>EGLL</origem>
    <destino>SBRF</destino>
    <temptrafego>95</temptrafego>
    <coord>
      <tipo>L</tipo>
      <cpoA>-7.69824</cpoA>
      <cpoB>-33.49384</cpoB>
    </coord>
    <altitude>470</altitude>
    <velocidade>480</velocidade>
    <proa>253</proa>
  </trafego>

  <trafego nTrf="108">
    <designador>B738</designador>
    <ssr>5226</ssr>
    <indicativo>GLO1632</indicativo>
    <origem>SBNT</origem>
    <destino>SBRF</destino>
    <temptrafego>115</temptrafego>
    <coord>
      <tipo>L</tipo>
      <cpoA>-5.90833</cpoA>
      <cpoB>-35.24867</cpoB>
    </coord>
    <altitude>20</altitude>
    <velocidade>210</velocidade>
    <procedimento>TRJ720018</procedimento>
  </trafego>

  <trafego nTrf="109">
    <designador>B777</designador>
    <ssr>5664</ssr>
    <indicativo>AAL981</indicativo>
    <origem>KMIA</origem>
    <destino>SBRF</destino>
    <temptrafego>147</temptrafego>
    <coord>
      <tipo>L</tipo>
      <cpoA>-6.95885</cpoA>
      <cpoB>-36.3308</cpoB>
    </coord>
    <altitude>380</altitude>
    <velocidade>480</velocidade>
    <proa>133</proa>
  </trafego>

  <trafego nTrf="110">
    <designador>A343</designador>
    <ssr>5227</ssr>
    <indicativo>TAP164</indicativo>
    <origem>LPPT</origem>
    <destino>SBRF</destino>
    <temptrafego>146</temptrafego>
    <coord>
      <tipo>L</tipo>
      <cpoA>-5.37304</cpoA>
      <cpoB>-34.61073</cpoB>
    </coord>
    <altitude>400</altitude>
    <velocidade>480</velocidade>
    <proa>230</proa>
  </trafego>

  <trafego nTrf="111">
    <designador>B738</designador>
    <ssr>5501</ssr>
    <indicativo>GLO1788</indicativo>
    <origem>SBGR</origem>
    <destino>SBRF</destino>
    <temptrafego>60</temptrafego>
    <coord>
      <tipo>L</tipo>
      <cpoA>-10.98167</cpoA>
      <cpoB>-37.07133</cpoB>
    </coord>
    <altitude>330</altitude>
    <velocidade>440</velocidade>
    <proa>60</proa>
  </trafego>

  <trafego nTrf="112">
    <designador>A320</designador>
    <ssr>5502</ssr>
    <indicativo>TAM3082</indicativo>
    <origem>SBGL</origem>
    <destino>SBRF</destino>
    <temptrafego>62</temptrafego>
    <coord>
      <tipo>L</tipo>
      <cpoA>-10.98167</cpoA>
      <cpoB>-37.07133</cpoB>
    </coord>
    <altitude>350</altitude>
    <velocidade>480</velocidade>
    <proa>60</proa>
  </trafego>

  <trafego nTrf="113">
    <designador>B777</designador>
    <ssr>5503</ssr>
    <indicativo>AAL983</indicativo>
    <origem>KMIA</origem>
    <destino>SBRF</destino>
    <temptrafego>60</temptrafego>
    <coord>
      <tipo>L</tipo>
      <cpoA>-6.20548</cpoA>
      <cpoB>-36.9981</cpoB>
    </coord>
    <altitude>340</altitude>
    <velocidade>470</velocidade>
    <proa>133</proa>
  </trafego>

  <trafego nTrf="114">
    <designador>B738</designador>
    <ssr>5504</ssr>
    <indicativo>GLO1876</indicativo>
    <origem>SBBR</origem>
    <destino>SBRF</destino>
    <temptrafego>62</temptrafego>
    <coord>
      <tipo>L</tipo>
      <cpoA>-9.51683</cpoA>
      <cpoB>-37.14767</cpoB>
    </coord>
    <altitude>390</altitude>
    <velocidade>480</velocidade>
    <proa>80</proa>
  </trafego>

  <trafego nTrf="115">
    <designador>A320</designador>
    <ssr>5505</ssr>
    <indicativo>TAM3894</indicativo>
    <origem>SBSV</origem>
    <destino>SBRF</destino>
    <temptrafego>65</temptrafego>
    <coord>
      <tipo>L</tipo>
      <cpoA>-10.98167</cpoA>
      <cpoB>-37.07133</cpoB>
    </coord>
    <altitude>370</altitude>
    <velocidade>480</velocidade>
    <proa>60</proa>
  </trafego>

  <trafego nTrf="116">
    <designador>A320</designador>
    <ssr>5506</ssr>
    <indicativo>TAM3517</indicativo>
    <origem>SBFZ</origem>
    <destino>SBRF</destino>
    <temptrafego>65</temptrafego>
    <coord>
      <tipo>L</tipo>
      <cpoA>-5.34916</cpoA>
      <cpoB>-35.77951</cpoB>
    </coord>
    <altitude>370</altitude>
    <velocidade>480</velocidade>
    <proa>163</proa>
  </trafego>

  <trafego nTrf="117">
    <designador>B738</designador>
    <ssr>5507</ssr>
    <indicativo>GLO1981</indicativo>
    <origem>SBPL</origem>
    <destino>SBRF</destino>
    <temptrafego>68</temptrafego>
    <coord>
      <tipo>L</tipo>
      <cpoA>-7.64483</cpoA>
      <cpoB>-37.71573</cpoB>
    </coord>
    <altitude>350</altitude>
    <velocidade>480</velocidade>
    <proa>100</proa>
  </trafego>

  <trafego nTrf="118">
    <designador>B738</designador>
    <ssr>5510</ssr>
    <indicativo>GLO1644</indicativo>
    <origem>SBSV</origem>
    <destino>SBRF</destino>
    <temptrafego>78</temptrafego>
    <coord>
      <tipo>L</tipo>
      <cpoA>-10.98167</cpoA>
      <cpoB>-37.07133</cpoB>
    </coord>
    <altitude>390</altitude>
    <velocidade>480</velocidade>
    <proa>60</proa>
  </trafego>

  <trafego nTrf="119">
    <designador>B757</designador>
    <ssr>5512</ssr>
    <indicativo>VLO6516</indicativo>
    <origem>SBBR</origem>
    <destino>SBRF</destino>
    <temptrafego>86</temptrafego>
    <coord>
      <tipo>L</tipo>
      <cpoA>-9.51683</cpoA>
      <cpoB>-37.14767</cpoB>
    </coord>
    <altitude>310</altitude>
    <velocidade>480</velocidade>
    <proa>80</proa>
  </trafego>

  <trafego nTrf="120">
    <designador>B733</designador>
    <ssr>5513</ssr>
    <indicativo>WEB6752</indicativo>
    <origem>SBBR</origem>
    <destino>SBRF</destino>
    <temptrafego>88</temptrafego>
    <coord>
      <tipo>L</tipo>
      <cpoA>-9.51683</cpoA>
      <cpoB>-37.14767</cpoB>
    </coord>
    <altitude>350</altitude>
    <velocidade>440</velocidade>
    <proa>80</proa>
  </trafego>

  <trafego nTrf="121">
    <designador>A320</designador>
    <ssr>5514</ssr>
    <indicativo>TAM3522</indicativo>
    <origem>SBGR</origem>
    <destino>SBRF</destino>
    <temptrafego>93</temptrafego>
    <coord>
      <tipo>L</tipo>
      <cpoA>-10.98167</cpoA>
      <cpoB>-37.07133</cpoB>
    </coord>
    <altitude>410</altitude>
    <velocidade>480</velocidade>
    <proa>60</proa>
  </trafego>

  <trafego nTrf="122">
    <designador>B738</designador>
    <ssr>5515</ssr>
    <indicativo>GLO1666</indicativo>
    <origem>SBGL</origem>
    <destino>SBRF</destino>
    <temptrafego>98</temptrafego>
    <coord>
      <tipo>L</tipo>
      <cpoA>-10.98167</cpoA>
      <cpoB>-37.07133</cpoB>
    </coord>
    <altitude>390</altitude>
    <velocidade>480</velocidade>
    <proa>60</proa>
  </trafego>

  <trafego nTrf="123">
    <designador>A340</designador>
    <ssr>5516</ssr>
    <indicativo>TAP153</indicativo>
    <origem>LPPT</origem>
    <destino>SBRF</destino>
    <temptrafego>68</temptrafego>
    <coord>
      <tipo>L</tipo>
      <cpoA>-5.15892</cpoA>
      <cpoB>-34.35555</cpoB>
    </coord>
    <altitude>380</altitude>
    <velocidade>480</velocidade>
    <proa>230</proa>
  </trafego>

  <trafego nTrf="124">
    <designador>A343</designador>
    <ssr>5517</ssr>
    <indicativo>ACC801</indicativo>
    <origem>LEMD</origem>
    <destino>SBRF</destino>
    <temptrafego>70</temptrafego>
    <coord>
      <tipo>L</tipo>
      <cpoA>-7.25998</cpoA>
      <cpoB>-32.06035</cpoB>
    </coord>
    <altitude>370</altitude>
    <velocidade>480</velocidade>
    <proa>253</proa>
  </trafego>

  <trafego nTrf="125">
    <designador>B738</designador>
    <ssr>5520</ssr>
    <indicativo>GLO1990</indicativo>
    <origem>SBFZ</origem>
    <destino>SBRF</destino>
    <temptrafego>75</temptrafego>
    <coord>
      <tipo>L</tipo>
      <cpoA>-5.52286</cpoA>
      <cpoB>-35.77655</cpoB>
    </coord>
    <altitude>370</altitude>
    <velocidade>480</velocidade>
    <proa>162</proa>
  </trafego>

  <trafego nTrf="126">
    <designador>B738</designador>
    <ssr>5521</ssr>
    <indicativo>GLO1677</indicativo>
    <origem>SBFN</origem>
    <destino>SBRF</destino>
    <temptrafego>50</temptrafego>
    <coord>
      <tipo>L</tipo>
      <cpoA>-3.86</cpoA>
      <cpoB>-32.43</cpoB>
    </coord>
    <altitude>20</altitude>
    <velocidade>210</velocidade>
    <procedimento>TRJ720017</procedimento>
  </trafego>

  <trafego nTrf="127">
    <designador>C750</designador>
    <ssr>5522</ssr>
    <indicativo>PTBRG</indicativo>
    <origem>SBFZ</origem>
    <destino>SBRF</destino>
    <temptrafego>0</temptrafego>
    <coord>
      <tipo>L</tipo>
      <cpoA>-7.72465</cpoA>
      <cpoB>-35.06115</cpoB>
    </coord>
    <altitude>70</altitude>
    <velocidade>250</velocidade>
    <proa>162</proa>
  </trafego>
</trafegos>

